{
  "type": "Feature",
  "properties": {
    "gn:admin1_code":"00",
    "gn:asciiname":"Pak Sha Tau",
    "gn:country_code":"HK",
    "gn:dem":6,
    "gn:feature_class":"P",
    "gn:feature_code":"PPL",
    "gn:name":"Pak Sha Tau",
    "gn:population":0,
    "gn:timezone":"Asia/Hong_Kong",
    "iso:country":"HK",
    "name:und_x_variant":[
        "Baishatou"
    ],
    "name:zho_x_preferred":[
        "\u767d\u6c99\u982d"
    ],
    "name:zho_x_variant":[
        "\u767d\u6c99\u5934"
    ],
    "wof:name":"Pak Sha Tau",
    "wof:placetype":"locality"
},
  "geometry": {"coordinates":[114.28659,22.53365],"type":"Point"}
}