{
  "type": "Feature",
  "properties": {
    "iso:country":"HK",
    "label:eng_x_preferred_longname":[
        "Kangle Village"
    ],
    "label:eng_x_preferred_placetype":[
        "village"
    ],
    "name:eng_x_preferred":[
        "Kangle"
    ],
    "name:eng_x_variant":[
        "Kangle Village"
    ],
    "name:zho_tw_x_preferred":[
        "\u5eb7\u6a02\u6751"
    ],
    "qs:gn_pop":0,
    "qs:name":"\u5eb7\u6a02\u6751",
    "qs:name_adm0":"\u9999\u6e2f",
    "qs:name_adm1":"\u65b0\u754c",
    "qs:photos":99,
    "qs:photos_1k":20,
    "qs:photos_9k":1,
    "qs:photos_9r":3,
    "qs:photos_all":99,
    "qs:photos_sr":3,
    "qs:placetype":"Town",
    "qs:pop_sr":"0",
    "qs:woe_adm0":24865698,
    "wof:name":"Kangle",
    "wof:placetype":"locality"
},
  "geometry": {"coordinates":[114.15430000000001,22.463071],"type":"Point"}
}