{
  "type": "Feature",
  "properties": {
    "gn:admin1_code":"NTM",
    "gn:asciiname":"Shek Pai Tau",
    "gn:country_code":"HK",
    "gn:dem":22,
    "gn:feature_class":"P",
    "gn:feature_code":"PPL",
    "gn:name":"Shek Pai Tau",
    "gn:population":0,
    "gn:timezone":"Asia/Hong_Kong",
    "iso:country":"HK",
    "name:und_x_variant":[
        "Shipaitou"
    ],
    "name:zho_x_preferred":[
        "\u77f3\u6392\u982d"
    ],
    "name:zho_x_variant":[
        "\u77f3\u6392\u5934"
    ],
    "wof:name":"Shek Pai Tau",
    "wof:placetype":"locality"
},
  "geometry": {"coordinates":[113.96766,22.40142],"type":"Point"}
}