{
  "type": "Feature",
  "properties": {
    "gn:admin1_code":"NYL",
    "gn:asciiname":"Hang Hau Tsuen",
    "gn:country_code":"HK",
    "gn:dem":0,
    "gn:feature_class":"P",
    "gn:feature_code":"PPL",
    "gn:name":"Hang Hau Tsuen",
    "gn:population":0,
    "gn:timezone":"Asia/Hong_Kong",
    "iso:country":"HK",
    "name:und_x_variant":[
        "Kengkou Cun"
    ],
    "name:zho_x_preferred":[
        "\u5751\u53e3\u6751"
    ],
    "wof:name":"Hang Hau Tsuen",
    "wof:placetype":"locality"
},
  "geometry": {"coordinates":[113.98166000000001,22.46441],"type":"Point"}
}