{
  "type": "Feature",
  "properties": {
    "gn:admin1_code":"NTM",
    "gn:asciiname":"Sha Po Kong",
    "gn:country_code":"HK",
    "gn:dem":6,
    "gn:feature_class":"P",
    "gn:feature_code":"PPL",
    "gn:name":"Sha Po Kong",
    "gn:population":0,
    "gn:timezone":"Asia/Hong_Kong",
    "iso:country":"HK",
    "name:und_x_variant":[
        "Shapugang",
        "Sha Po Kong"
    ],
    "wof:name":"Sha Po Kong",
    "wof:placetype":"locality"
},
  "geometry": {"coordinates":[113.92157,22.389],"type":"Point"}
}