{
  "type": "Feature",
  "properties": {
    "iso:country":"HK",
    "name:chi_x_preferred":[
        "\u8475\u6d8c"
    ],
    "name:dut_x_preferred":[
        "Kwai Chung"
    ],
    "name:eng_x_preferred":[
        "Kwai Chung"
    ],
    "name:fre_x_preferred":[
        "Kwai Chung"
    ],
    "name:ger_x_preferred":[
        "Kwai Chung"
    ],
    "name:jpn_x_preferred":[
        "\u8475\u6d8c"
    ],
    "name:kor_x_preferred":[
        "\ucfe0\uc774\ucda9"
    ],
    "name:srp_x_preferred":[
        "\u041a\u0432\u0430\u0458 \u0427\u0443\u043d\u0433"
    ],
    "name:swe_x_preferred":[
        "Kuiyong"
    ],
    "name:tam_x_preferred":[
        "\u0b95\u0bc1\u0bb5\u0bbe\u0baf\u0bcd \u0b9a\u0bc1\u0b99\u0bcd"
    ],
    "name:unk_x_variant":[
        "Kwai Chung"
    ],
    "name:yue_x_preferred":[
        "\u8475\u6d8c"
    ],
    "name:zho_x_preferred":[
        "\u4e0b\u8475\u6d8c"
    ],
    "qs:gn_country":"HK",
    "qs:gn_fcode":"PPL",
    "qs:gn_pop":0,
    "qs:name":"\u4e0b\u8475\u6d8c",
    "qs:name_adm0":"\u9999\u6e2f",
    "qs:name_adm1":"\u65b0\u754c",
    "qs:photos":3507,
    "qs:photos_1k":711,
    "qs:photos_9k":16,
    "qs:photos_9r":12,
    "qs:photos_all":3507,
    "qs:photos_sr":21,
    "qs:placetype":"Town",
    "qs:pop_sr":"0",
    "qs:woe_adm0":24865698,
    "wof:name":"\u4e0b\u8475\u6d8c",
    "wof:placetype":"locality"
},
  "geometry": {"coordinates":[114.13333,22.35],"type":"Point"}
}