{
  "type": "Feature",
  "properties": {
    "gn:admin1_code":"HWC",
    "gn:asciiname":"Wan Chai",
    "gn:country_code":"HK",
    "gn:dem":40,
    "gn:feature_class":"P",
    "gn:feature_code":"PPLA",
    "gn:name":"Wan Chai",
    "gn:population":0,
    "gn:timezone":"Asia/Hong_Kong",
    "iso:country":"HK",
    "name:ara_x_preferred":[
        "\u0648\u0627\u0646 \u062a\u0634\u0627\u064a"
    ],
    "name:deu_x_preferred":[
        "Wan Chai"
    ],
    "name:eng_x_preferred":[
        "Wanchai"
    ],
    "name:fra_x_preferred":[
        "Wan Chai"
    ],
    "name:ind_x_preferred":[
        "Wan Chai"
    ],
    "name:kor_x_preferred":[
        "\uc644 \ucc28\uc774"
    ],
    "name:kor_x_variant":[
        "\uc644\uc790\uc774"
    ],
    "name:nld_x_preferred":[
        "Wan Chai"
    ],
    "name:pol_x_preferred":[
        "Wan Chai"
    ],
    "name:por_x_preferred":[
        "Wan Chai"
    ],
    "name:rus_x_preferred":[
        "\u0412\u0430\u043d\u044c\u0447\u0430\u0439"
    ],
    "name:swe_x_preferred":[
        "Wan Chai"
    ],
    "name:tam_x_preferred":[
        "\u0bb5\u0b9e\u0bcd\u0b9a\u0bbe\u0baf\u0bcd"
    ],
    "name:tur_x_preferred":[
        "Wan Chai"
    ],
    "name:ukr_x_preferred":[
        "\u0412\u0430\u043d\u0447\u0430\u0456"
    ],
    "name:urd_x_preferred":[
        "\u0648\u0627\u0646 \u0686\u0627\u0626\u06cc"
    ],
    "name:vie_x_preferred":[
        "Loan T\u1ec3"
    ],
    "name:zho_cn_x_preferred":[
        "\u6e7e\u4ed4"
    ],
    "name:zho_tw_x_preferred":[
        "\u7063\u4ed4"
    ],
    "name:zho_x_preferred":[
        "\u7063\u4ed4"
    ],
    "wof:name":"Wan Chai",
    "wof:placetype":"locality"
},
  "geometry": {"coordinates":[114.17258,22.28142],"type":"Point"}
}