{
  "type": "Feature",
  "properties": {
    "gn:admin1_code":"HWC",
    "gn:asciiname":"Wan Chai",
    "gn:country_code":"HK",
    "gn:dem":40,
    "gn:feature_class":"P",
    "gn:feature_code":"PPLA",
    "gn:name":"Wan Chai",
    "gn:population":0,
    "gn:timezone":"Asia/Hong_Kong",
    "iso:country":"HK",
    "name:eng_x_preferred":[
        "Wanchai"
    ],
    "name:zho_x_preferred":[
        "\u7063\u4ed4"
    ],
    "wof:name":"Wan Chai",
    "wof:placetype":"locality"
},
  "geometry": {"coordinates":[114.17258,22.28142],"type":"Point"}
}