{
  "type": "Feature",
  "properties": {
    "gn:admin1_code":"NIS",
    "gn:asciiname":"Lower Keung Shan",
    "gn:country_code":"HK",
    "gn:dem":102,
    "gn:feature_class":"P",
    "gn:feature_code":"PPL",
    "gn:name":"Lower Keung Shan",
    "gn:population":0,
    "gn:timezone":"Asia/Hong_Kong",
    "iso:country":"HK",
    "name:und_x_variant":[
        "Keung Shan",
        "Lower Keung Shan",
        "Xiaqiang"
    ],
    "name:zho_x_preferred":[
        "\u4e0b\u7f97"
    ],
    "wof:name":"Lower Keung Shan",
    "wof:placetype":"locality"
},
  "geometry": {"coordinates":[113.87926000000002,22.24783],"type":"Point"}
}