{
  "type": "Feature",
  "properties": {
    "gn:admin1_code":"NTP",
    "gn:asciiname":"Ha Wai",
    "gn:country_code":"HK",
    "gn:dem":4,
    "gn:feature_class":"P",
    "gn:feature_code":"PPL",
    "gn:name":"Ha Wai",
    "gn:population":0,
    "gn:timezone":"Asia/Hong_Kong",
    "iso:country":"HK",
    "name:und_x_variant":[
        "Xiawei"
    ],
    "name:zho_x_preferred":[
        "\u4e0b\u570d"
    ],
    "name:zho_x_variant":[
        "\u4e0b\u56f4"
    ],
    "wof:name":"Ha Wai",
    "wof:placetype":"locality"
},
  "geometry": {"coordinates":[114.36039,22.47223],"type":"Point"}
}