{
  "type": "Feature",
  "properties": {
    "iso:country":"HK",
    "name:unk_x_variant":[
        "Tsing Tau"
    ],
    "name:zho_x_preferred":[
        "\u4e95\u982d"
    ],
    "name:zho_x_variant":[
        "\u4e95\u5934"
    ],
    "qs:gn_country":"HK",
    "qs:gn_fcode":"PPL",
    "qs:gn_pop":0,
    "qs:name":"\u4e95\u982d",
    "qs:name_adm0":"\u9999\u6e2f",
    "qs:name_adm1":"\u65b0\u754c",
    "qs:photos":148,
    "qs:photos_1k":30,
    "qs:photos_9k":1,
    "qs:photos_9r":3,
    "qs:photos_all":148,
    "qs:photos_sr":3,
    "qs:placetype":"Town",
    "qs:pop_sr":"0",
    "qs:woe_adm0":24865698,
    "wof:name":"\u4e95\u982d",
    "wof:placetype":"locality"
},
  "geometry": {"coordinates":[114.26667,22.43333],"type":"Point"}
}