{
  "type": "Feature",
  "properties": {
    "gn:admin1_code":"NYL",
    "gn:asciiname":"Sheung Chuk Yuen",
    "gn:country_code":"HK",
    "gn:dem":3,
    "gn:feature_class":"P",
    "gn:feature_code":"PPL",
    "gn:name":"Sheung Chuk Yuen",
    "gn:population":0,
    "gn:timezone":"Asia/Hong_Kong",
    "iso:country":"HK",
    "name:und_x_variant":[
        "Shangzhu Wei"
    ],
    "name:zho_x_preferred":[
        "\u4e0a\u7af9\u570d"
    ],
    "name:zho_x_variant":[
        "\u4e0a\u7af9\u56f4"
    ],
    "wof:name":"Sheung Chuk Yuen",
    "wof:placetype":"locality"
},
  "geometry": {"coordinates":[114.05826999999999,22.47482],"type":"Point"}
}