{
  "type": "Feature",
  "properties": {
    "gn:admin1_code":"00",
    "gn:asciiname":"Siu A Chau Tsuen",
    "gn:country_code":"HK",
    "gn:dem":16,
    "gn:feature_class":"P",
    "gn:feature_code":"PPL",
    "gn:name":"Siu A Chau Tsuen",
    "gn:population":0,
    "gn:timezone":"Asia/Hong_Kong",
    "iso:country":"HK",
    "name:und_x_variant":[
        "Xiaoya Zhou Cun"
    ],
    "name:zho_x_preferred":[
        "\u5c0f\u9d09\u6d32\u6751"
    ],
    "name:zho_x_variant":[
        "\u5c0f\u9e26\u6d32\u6751"
    ],
    "wof:name":"Siu A Chau Tsuen",
    "wof:placetype":"locality"
},
  "geometry": {"coordinates":[113.91092999999999,22.18248],"type":"Point"}
}