{
  "type": "Feature",
  "properties": {
    "gn:admin1_code":"NTP",
    "gn:asciiname":"Tai Po",
    "gn:country_code":"HK",
    "gn:dem":3,
    "gn:feature_class":"P",
    "gn:feature_code":"PPL",
    "gn:name":"Tai Po",
    "gn:population":0,
    "gn:timezone":"Asia/Hong_Kong",
    "iso:country":"HK",
    "name:ceb_x_preferred":[
        "Tai Po"
    ],
    "name:srp_x_preferred":[
        "\u0422\u0430\u0458 \u041f\u043e"
    ],
    "name:und_x_variant":[
        "Dapu"
    ],
    "name:zho_x_preferred":[
        "\u5927\u57d4"
    ],
    "wof:name":"Tai Po",
    "wof:placetype":"locality"
},
  "geometry": {"coordinates":[113.92193,22.29005],"type":"Point"}
}