{
  "type": "Feature",
  "properties": {
    "gn:admin1_code":"NTP",
    "gn:asciiname":"Tai Po",
    "gn:country_code":"HK",
    "gn:dem":3,
    "gn:feature_class":"P",
    "gn:feature_code":"PPL",
    "gn:name":"Tai Po",
    "gn:population":0,
    "gn:timezone":"Asia/Hong_Kong",
    "iso:country":"HK",
    "name:ara_x_preferred":[
        "\u062a\u0627\u064a \u0628\u0648"
    ],
    "name:ben_x_preferred":[
        "\u09a4\u09be\u0987 \u09aa\u09cb"
    ],
    "name:ceb_x_preferred":[
        "Tai Po"
    ],
    "name:deu_x_preferred":[
        "Tai Po"
    ],
    "name:ell_x_preferred":[
        "\u03a4\u03ac\u03b9 \u03a0\u03bf"
    ],
    "name:eng_x_preferred":[
        "Tai Po"
    ],
    "name:fas_x_preferred":[
        "\u062a\u0627\u06cc \u067e\u0648"
    ],
    "name:fra_x_preferred":[
        "Tai Po"
    ],
    "name:heb_x_preferred":[
        "\u05d8\u05d0\u05d9 \u05e4\u05d5"
    ],
    "name:hin_x_preferred":[
        "\u0924\u093e\u0908 \u092a\u094b"
    ],
    "name:hun_x_preferred":[
        "Tai Po"
    ],
    "name:ind_x_preferred":[
        "Tai Po"
    ],
    "name:ita_x_preferred":[
        "Tai Po"
    ],
    "name:jpn_x_preferred":[
        "\u30bf\u30a4\u30dd\u30fc"
    ],
    "name:kor_x_preferred":[
        "\ud0c0\uc774 \ud3ec"
    ],
    "name:nld_x_preferred":[
        "Tai Po"
    ],
    "name:pol_x_preferred":[
        "Tai Po"
    ],
    "name:por_x_preferred":[
        "Tai Po"
    ],
    "name:rus_x_preferred":[
        "\u0422\u0430\u0439\u043f\u043e\u0443"
    ],
    "name:spa_x_preferred":[
        "Tai Po"
    ],
    "name:srp_x_preferred":[
        "\u0422\u0430\u0458 \u041f\u043e"
    ],
    "name:swe_x_preferred":[
        "Tai Po"
    ],
    "name:tur_x_preferred":[
        "Tai Po"
    ],
    "name:ukr_x_preferred":[
        "\u0422\u0430\u0439\u043f\u043e"
    ],
    "name:und_x_variant":[
        "Dapu"
    ],
    "name:urd_x_preferred":[
        "\u062a\u0627\u0626\u06cc \u067e\u0648"
    ],
    "name:vie_x_preferred":[
        "\u0110\u1ea1i B\u1ed9"
    ],
    "name:zho_cn_x_preferred":[
        "\u5927\u57d4"
    ],
    "name:zho_tw_x_preferred":[
        "\u5927\u57d4"
    ],
    "name:zho_x_preferred":[
        "\u5927\u57d4"
    ],
    "wof:name":"Tai Po",
    "wof:placetype":"locality"
},
  "geometry": {"coordinates":[113.92193,22.29005],"type":"Point"}
}