{
  "type": "Feature",
  "properties": {
    "iso:country":"HK",
    "name:ceb_x_preferred":[
        "Ocean Park"
    ],
    "name:deu_x_preferred":[
        "Ocean Park"
    ],
    "name:swe_x_preferred":[
        "Ocean Park"
    ],
    "name:zho_x_preferred":[
        "\u6d77\u6d0b\u516c\u5712"
    ],
    "qs:gn_pop":0,
    "qs:name":"Ocean Park",
    "qs:name_adm0":"\u9999\u6e2f",
    "qs:name_adm1":"\u6e2f\u5cf6",
    "qs:photos":599,
    "qs:photos_1k":121,
    "qs:photos_9k":3,
    "qs:photos_9r":5,
    "qs:photos_all":599,
    "qs:photos_sr":8,
    "qs:placetype":"Town",
    "qs:pop_sr":"0",
    "qs:woe_adm0":24865698,
    "wd:wordcount":60,
    "wof:name":"Ocean Park",
    "wof:placetype":"locality"
},
  "geometry": {"coordinates":[114.170458,22.234337],"type":"Point"}
}