{
  "type": "Feature",
  "properties": {
    "gn:admin1_code":"NIS",
    "gn:asciiname":"Chung Hau",
    "gn:country_code":"HK",
    "gn:dem":9,
    "gn:feature_class":"P",
    "gn:feature_code":"PPL",
    "gn:name":"Chung Hau",
    "gn:population":0,
    "gn:timezone":"Asia/Hong_Kong",
    "iso:country":"HK",
    "name:und_x_variant":[
        "Chongkou"
    ],
    "name:zho_x_preferred":[
        "\u6d8c\u53e3"
    ],
    "wof:name":"Chung Hau",
    "wof:placetype":"locality"
},
  "geometry": {"coordinates":[113.99603,22.26841],"type":"Point"}
}