{
  "type": "Feature",
  "properties": {
    "iso:country":"HK",
    "name:eng_x_preferred":[
        "Pui O San Wai Tsuen"
    ],
    "name:zho_hk_x_preferred":[
        "\u6fb3\u8c9d\u65b0\u6751"
    ],
    "qs:gn_pop":0,
    "qs:name":"\u6fb3\u8c9d\u65b0\u6751",
    "qs:name_adm0":"\u9999\u6e2f",
    "qs:name_adm1":"\u96e2\u5cf6",
    "qs:photos":1250,
    "qs:photos_1k":253,
    "qs:photos_9k":6,
    "qs:photos_9r":7,
    "qs:photos_all":1250,
    "qs:photos_sr":11,
    "qs:placetype":"Town",
    "qs:pop_sr":"0",
    "qs:woe_adm0":24865698,
    "wof:name":"Pui O San Wai Tsuen",
    "wof:placetype":"locality"
},
  "geometry": {"coordinates":[113.976716,22.240484],"type":"Point"}
}