{
  "type": "Feature",
  "properties": {
    "iso:country":"HK",
    "qs:gn_pop":0,
    "qs:name":"\u5357\u6f6d",
    "qs:name_adm0":"\u9999\u6e2f",
    "qs:name_adm1":"\u96e2\u5cf6",
    "qs:photos":297,
    "qs:photos_1k":60,
    "qs:photos_9k":1,
    "qs:photos_9r":4,
    "qs:photos_all":297,
    "qs:photos_sr":5,
    "qs:placetype":"Town",
    "qs:pop_sr":"0",
    "qs:woe_adm0":24865698,
    "wof:name":"\u5357\u6f6d",
    "wof:placetype":"locality"
},
  "geometry": {"coordinates":[114.033249,22.205023],"type":"Point"}
}