{
  "type": "Feature",
  "properties": {
    "gn:admin1_code":"NST",
    "gn:asciiname":"Lo Shue Tin",
    "gn:country_code":"HK",
    "gn:dem":251,
    "gn:feature_class":"P",
    "gn:feature_code":"PPL",
    "gn:name":"Lo Shue Tin",
    "gn:population":0,
    "gn:timezone":"Asia/Hong_Kong",
    "iso:country":"HK",
    "name:und_x_variant":[
        "Laoshatian"
    ],
    "name:zho_x_preferred":[
        "\u8001\u6c99\u7530"
    ],
    "wof:name":"Lo Shue Tin",
    "wof:placetype":"locality"
},
  "geometry": {"coordinates":[114.22253000000001,22.37128],"type":"Point"}
}