{
  "type": "Feature",
  "properties": {
    "gn:admin1_code":"NNO",
    "gn:asciiname":"Mo To Tang",
    "gn:country_code":"HK",
    "gn:dem":30,
    "gn:feature_class":"P",
    "gn:feature_code":"PPL",
    "gn:name":"Mo To Tang",
    "gn:population":0,
    "gn:timezone":"Asia/Hong_Kong",
    "iso:country":"HK",
    "name:und_x_variant":[
        "Modaokeng"
    ],
    "name:zho_x_preferred":[
        "\u78e8\u5200\u5751"
    ],
    "wof:name":"Mo To Tang",
    "wof:placetype":"locality"
},
  "geometry": {"coordinates":[114.27212,22.52438],"type":"Point"}
}