{
  "type": "Feature",
  "properties": {
    "gn:admin1_code":"NNO",
    "gn:asciiname":"Tung Kok Wai",
    "gn:country_code":"HK",
    "gn:dem":12,
    "gn:feature_class":"P",
    "gn:feature_code":"PPL",
    "gn:name":"Tung Kok Wai",
    "gn:population":0,
    "gn:timezone":"Asia/Hong_Kong",
    "iso:country":"HK",
    "name:und_x_variant":[
        "Dongge Wei"
    ],
    "name:zho_x_preferred":[
        "\u6771\u95a3\u570d"
    ],
    "name:zho_x_variant":[
        "\u4e1c\u9601\u56f4"
    ],
    "wof:name":"Tung Kok Wai",
    "wof:placetype":"locality"
},
  "geometry": {"coordinates":[114.15276,22.5004],"type":"Point"}
}