{
  "type": "Feature",
  "properties": {
    "gn:admin1_code":"NNO",
    "gn:asciiname":"Tong To",
    "gn:country_code":"HK",
    "gn:dem":40,
    "gn:feature_class":"P",
    "gn:feature_code":"PPL",
    "gn:name":"Tong To",
    "gn:population":0,
    "gn:timezone":"Asia/Hong_Kong",
    "iso:country":"HK",
    "name:und_x_variant":[
        "Tangdu"
    ],
    "name:zho_x_preferred":[
        "\u5858\u809a"
    ],
    "wof:name":"Tong To",
    "wof:placetype":"locality"
},
  "geometry": {"coordinates":[114.21124,22.54267],"type":"Point"}
}