{
  "type": "Feature",
  "properties": {
    "gn:admin1_code":"NYL",
    "gn:asciiname":"Lok Ma Chau",
    "gn:cc2":"HK",
    "gn:country_code":"HK",
    "gn:dem":7,
    "gn:feature_class":"P",
    "gn:feature_code":"PPL",
    "gn:name":"Lok Ma Chau",
    "gn:population":0,
    "gn:timezone":"Asia/Hong_Kong",
    "iso:country":"HK",
    "name:hak_x_preferred":[
        "Lo\u030dk-m\u00e2-ch\u00fb"
    ],
    "name:nld_x_preferred":[
        "Lok Ma Chau"
    ],
    "name:und_x_variant":[
        "Lak Ma Chau"
    ],
    "name:wuu_x_preferred":[
        "\u843d\u9a6c\u6d32"
    ],
    "name:zho_x_preferred":[
        "\u843d\u99ac\u6d32"
    ],
    "wof:name":"Lok Ma Chau",
    "wof:placetype":"locality"
},
  "geometry": {"coordinates":[114.07916000000002,22.50946],"type":"Point"}
}