{
  "type": "Feature",
  "properties": {
    "iso:country":"HK",
    "name:unk_x_variant":[
        "Tan Ka Wan"
    ],
    "name:zho_x_preferred":[
        "\u86cb\u5bb6\u7063"
    ],
    "name:zho_x_variant":[
        "\u86cb\u5bb6\u6e7e"
    ],
    "qs:gn_country":"HK",
    "qs:gn_fcode":"PPL",
    "qs:gn_pop":0,
    "qs:name":"\u86cb\u5bb6\u7063",
    "qs:name_adm0":"\u9999\u6e2f",
    "qs:name_adm1":"\u65b0\u754c",
    "qs:photos":1784,
    "qs:photos_1k":361,
    "qs:photos_9k":8,
    "qs:photos_9r":8,
    "qs:photos_all":1784,
    "qs:photos_sr":14,
    "qs:placetype":"Town",
    "qs:pop_sr":"0",
    "qs:woe_adm0":24865698,
    "wof:name":"\u86cb\u5bb6\u7063",
    "wof:placetype":"locality"
},
  "geometry": {"coordinates":[114.34999999999999,22.45],"type":"Point"}
}