{
  "type": "Feature",
  "properties": {
    "gn:admin1_code":"NYL",
    "gn:asciiname":"Pak Sha Tsai",
    "gn:country_code":"HK",
    "gn:dem":12,
    "gn:feature_class":"P",
    "gn:feature_code":"PPL",
    "gn:name":"Pak Sha Tsai",
    "gn:population":0,
    "gn:timezone":"Asia/Hong_Kong",
    "iso:country":"HK",
    "name:und_x_variant":[
        "Baishazai"
    ],
    "name:zho_x_preferred":[
        "\u767d\u6c99\u4ed4"
    ],
    "wof:name":"Pak Sha Tsai",
    "wof:placetype":"locality"
},
  "geometry": {"coordinates":[114.01667,22.45],"type":"Point"}
}