{
  "type": "Feature",
  "properties": {
    "gn:admin1_code":"NTP",
    "gn:asciiname":"Sha Tau",
    "gn:country_code":"HK",
    "gn:dem":31,
    "gn:feature_class":"P",
    "gn:feature_code":"PPL",
    "gn:name":"Sha Tau",
    "gn:population":0,
    "gn:timezone":"Asia/Hong_Kong",
    "iso:country":"HK",
    "name:und_x_variant":[
        "Shatou"
    ],
    "name:zho_x_preferred":[
        "\u6c99\u982d"
    ],
    "name:zho_x_variant":[
        "\u6c99\u5934"
    ],
    "wof:name":"Sha Tau",
    "wof:placetype":"locality"
},
  "geometry": {"coordinates":[114.3566,22.42358],"type":"Point"}
}