{
  "type": "Feature",
  "properties": {
    "iso:country":"HK",
    "name:unk_x_variant":[
        "Sham Wan Tsuen"
    ],
    "name:zho_x_preferred":[
        "\u6df1\u7063\u6751"
    ],
    "name:zho_x_variant":[
        "\u6df1\u6e7e\u6751"
    ],
    "qs:gn_country":"HK",
    "qs:gn_fcode":"PPL",
    "qs:gn_pop":0,
    "qs:name":"\u6df1\u7063\u6751",
    "qs:name_adm0":"\u9999\u6e2f",
    "qs:name_adm1":"\u96e2\u5cf6",
    "qs:photos":3592,
    "qs:photos_1k":728,
    "qs:photos_9k":16,
    "qs:photos_9r":12,
    "qs:photos_all":3592,
    "qs:photos_sr":21,
    "qs:placetype":"Town",
    "qs:pop_sr":"0",
    "qs:woe_adm0":24865698,
    "wof:name":"\u6df1\u7063\u6751",
    "wof:placetype":"locality"
},
  "geometry": {"coordinates":[113.93333,22.31667],"type":"Point"}
}