{
  "type": "Feature",
  "properties": {
    "iso:country":"HK",
    "name:eng_x_preferred":[
        "Central Kwai Chung"
    ],
    "name:zho_hk_x_preferred":[
        "\u4e2d\u8475\u6d8c"
    ],
    "qs:gn_pop":0,
    "qs:name":"\u4e2d\u8475\u6d8c",
    "qs:name_adm0":"\u9999\u6e2f",
    "qs:name_adm1":"\u65b0\u754c",
    "qs:photos":1029,
    "qs:photos_1k":209,
    "qs:photos_9k":5,
    "qs:photos_9r":7,
    "qs:photos_all":1029,
    "qs:photos_sr":11,
    "qs:placetype":"Town",
    "qs:pop_sr":"0",
    "qs:woe_adm0":24865698,
    "wof:name":"Central Kwai Chung",
    "wof:placetype":"locality"
},
  "geometry": {"coordinates":[114.1266,22.375397],"type":"Point"}
}