{
  "type": "Feature",
  "properties": {
    "gn:admin1_code":"NYL",
    "gn:asciiname":"San Lung Tsuen",
    "gn:country_code":"HK",
    "gn:dem":6,
    "gn:feature_class":"P",
    "gn:feature_code":"PPL",
    "gn:name":"San Lung Tsuen",
    "gn:population":0,
    "gn:timezone":"Asia/Hong_Kong",
    "iso:country":"HK",
    "name:und_x_variant":[
        "Xinlong Cun"
    ],
    "name:zho_x_preferred":[
        "\u65b0\u9f8d\u6751"
    ],
    "name:zho_x_variant":[
        "\u65b0\u9f99\u6751"
    ],
    "wof:name":"San Lung Tsuen",
    "wof:placetype":"locality"
},
  "geometry": {"coordinates":[114.07288,22.49842],"type":"Point"}
}