{
  "type": "Feature",
  "properties": {
    "iso:country":"HK",
    "qs:gn_pop":0,
    "qs:name":"\u7d05\u5c71\u534a\u5cf6",
    "qs:name_adm0":"\u9999\u6e2f",
    "qs:name_adm1":"\u6e2f\u5cf6",
    "qs:photos":447,
    "qs:photos_1k":91,
    "qs:photos_9k":2,
    "qs:photos_9r":5,
    "qs:photos_all":447,
    "qs:photos_sr":6,
    "qs:placetype":"Town",
    "qs:pop_sr":"0",
    "qs:woe_adm0":24865698,
    "wof:name":"\u7d05\u5c71\u534a\u5cf6",
    "wof:placetype":"locality"
},
  "geometry": {"coordinates":[114.22195600000001,22.237127],"type":"Point"}
}