{
  "type": "Feature",
  "properties": {
    "gn:admin1_code":"NST",
    "gn:asciiname":"Kuk Liu",
    "gn:country_code":"HK",
    "gn:dem":187,
    "gn:feature_class":"P",
    "gn:feature_code":"PPL",
    "gn:name":"Kuk Liu",
    "gn:population":0,
    "gn:timezone":"Asia/Hong_Kong",
    "iso:country":"HK",
    "name:und_x_variant":[
        "Guliao"
    ],
    "name:zho_x_preferred":[
        "\u7a40\u5bee"
    ],
    "name:zho_x_variant":[
        "\u8c37\u5bee"
    ],
    "wof:name":"Kuk Liu",
    "wof:placetype":"locality"
},
  "geometry": {"coordinates":[114.16667,22.38333],"type":"Point"}
}