{
  "type": "Feature",
  "properties": {
    "gn:admin1_code":"NST",
    "gn:asciiname":"Hin Tin",
    "gn:country_code":"HK",
    "gn:dem":25,
    "gn:feature_class":"P",
    "gn:feature_code":"PPL",
    "gn:name":"Hin Tin",
    "gn:population":0,
    "gn:timezone":"Asia/Hong_Kong",
    "iso:country":"HK",
    "name:und_x_variant":[
        "Xiantian"
    ],
    "name:zho_x_preferred":[
        "\u986f\u7530"
    ],
    "name:zho_x_variant":[
        "\u663e\u7530"
    ],
    "wof:name":"Hin Tin",
    "wof:placetype":"locality"
},
  "geometry": {"coordinates":[114.17287,22.36184],"type":"Point"}
}