{
  "type": "Feature",
  "properties": {
    "iso:country":"HK",
    "name:und_x_variant":[
        "Sham Wat"
    ],
    "name:zho_x_preferred":[
        "\u6df1\u5c48"
    ],
    "qs:gn_country":"HK",
    "qs:gn_fcode":"PPL",
    "qs:gn_pop":0,
    "qs:name":"\u6df1\u4e95",
    "qs:name_adm0":"\u9999\u6e2f",
    "qs:name_adm1":"\u96e2\u5cf6",
    "qs:photos":168,
    "qs:photos_1k":34,
    "qs:photos_9k":1,
    "qs:photos_9r":4,
    "qs:photos_all":168,
    "qs:photos_sr":4,
    "qs:placetype":"Town",
    "qs:pop_sr":"0",
    "qs:woe_adm0":24865698,
    "wof:name":"\u6df1\u4e95",
    "wof:placetype":"locality"
},
  "geometry": {"coordinates":[113.88254999999999,22.26958],"type":"Point"}
}