{
  "type": "Feature",
  "properties": {
    "iso:country":"HK",
    "name:und_x_variant":[
        "Shan Tsui"
    ],
    "name:zho_x_preferred":[
        "\u5c71\u5480"
    ],
    "qs:gn_country":"HK",
    "qs:gn_fcode":"PPL",
    "qs:gn_pop":0,
    "qs:name":"\u5c71\u7fe0",
    "qs:name_adm0":"\u9999\u6e2f",
    "qs:name_adm1":"\u65b0\u754c",
    "qs:photos":458,
    "qs:photos_1k":93,
    "qs:photos_9k":2,
    "qs:photos_9r":5,
    "qs:photos_all":458,
    "qs:photos_sr":7,
    "qs:placetype":"Town",
    "qs:pop_sr":"0",
    "qs:woe_adm0":24865698,
    "wof:name":"\u5c71\u7fe0",
    "wof:placetype":"locality"
},
  "geometry": {"coordinates":[114.21666999999999,22.55],"type":"Point"}
}