{
  "type": "Feature",
  "properties": {
    "gn:admin1_code":"NYL",
    "gn:asciiname":"Lo Uk Tsuen",
    "gn:country_code":"HK",
    "gn:dem":32,
    "gn:feature_class":"P",
    "gn:feature_code":"PPL",
    "gn:name":"Lo Uk Tsuen",
    "gn:population":0,
    "gn:timezone":"Asia/Hong_Kong",
    "iso:country":"HK",
    "name:und_x_variant":[
        "Luowucun"
    ],
    "name:zho_x_preferred":[
        "\u7f85\u5c4b\u6751"
    ],
    "name:zho_x_variant":[
        "\u7f57\u5c4b\u6751"
    ],
    "wof:name":"Lo Uk Tsuen",
    "wof:placetype":"locality"
},
  "geometry": {"coordinates":[114.09632999999999,22.43028],"type":"Point"}
}