{
  "type": "Feature",
  "properties": {
    "gn:admin1_code":"NIS",
    "gn:asciiname":"Leung Uk",
    "gn:country_code":"HK",
    "gn:dem":6,
    "gn:feature_class":"P",
    "gn:feature_code":"PPL",
    "gn:name":"Leung Uk",
    "gn:population":0,
    "gn:timezone":"Asia/Hong_Kong",
    "iso:country":"HK",
    "name:und_x_variant":[
        "Liangwu"
    ],
    "name:zho_x_preferred":[
        "\u6881\u5c4b"
    ],
    "wof:name":"Leung Uk",
    "wof:placetype":"locality"
},
  "geometry": {"coordinates":[113.86535000000001,22.24863],"type":"Point"}
}