{
  "type": "Feature",
  "properties": {
    "gn:admin1_code":"NTP",
    "gn:asciiname":"Tai Po Kau Lo Wai",
    "gn:country_code":"HK",
    "gn:dem":14,
    "gn:feature_class":"P",
    "gn:feature_code":"PPL",
    "gn:name":"Tai Po Kau Lo Wai",
    "gn:population":0,
    "gn:timezone":"Asia/Hong_Kong",
    "iso:country":"HK",
    "name:und_x_variant":[
        "Dabujiao Laowei",
        "Dapujiao Laowei"
    ],
    "name:zho_x_preferred":[
        "\u5927\u57d4\u6ed8\u8001\u570d"
    ],
    "name:zho_x_variant":[
        "\u5927\u57d4\u6ed8\u8001\u56f4"
    ],
    "wof:name":"Tai Po Kau Lo Wai",
    "wof:placetype":"locality"
},
  "geometry": {"coordinates":[114.19273,22.43947],"type":"Point"}
}