{
  "type": "Feature",
  "properties": {
    "gn:admin1_code":"NST",
    "gn:asciiname":"Fa Sam Hang",
    "gn:country_code":"HK",
    "gn:dem":110,
    "gn:feature_class":"P",
    "gn:feature_code":"PPL",
    "gn:name":"Fa Sam Hang",
    "gn:population":0,
    "gn:timezone":"Asia/Hong_Kong",
    "iso:country":"HK",
    "name:und_x_variant":[
        "Huaxinkeng"
    ],
    "name:zho_x_preferred":[
        "\u82b1\u5fc3\u5751"
    ],
    "wof:name":"Fa Sam Hang",
    "wof:placetype":"locality"
},
  "geometry": {"coordinates":[114.22205,22.3819],"type":"Point"}
}