{
  "type": "Feature",
  "properties": {
    "gn:admin1_code":"NSK",
    "gn:asciiname":"Siu Chik Sha",
    "gn:country_code":"HK",
    "gn:dem":35,
    "gn:feature_class":"P",
    "gn:feature_code":"PPL",
    "gn:name":"Siu Chik Sha",
    "gn:population":0,
    "gn:timezone":"Asia/Hong_Kong",
    "iso:country":"HK",
    "name:und_x_variant":[
        "Xiaochisha"
    ],
    "name:zho_x_preferred":[
        "\u5c0f\u8d64\u6c99"
    ],
    "wof:name":"Siu Chik Sha",
    "wof:placetype":"locality"
},
  "geometry": {"coordinates":[114.27471,22.30086],"type":"Point"}
}