{
  "type": "Feature",
  "properties": {
    "gn:admin1_code":"NTP",
    "gn:asciiname":"Wong Chuk Yeung",
    "gn:country_code":"HK",
    "gn:dem":221,
    "gn:feature_class":"P",
    "gn:feature_code":"PPL",
    "gn:name":"Wong Chuk Yeung",
    "gn:population":0,
    "gn:timezone":"Asia/Hong_Kong",
    "iso:country":"HK",
    "name:und_x_variant":[
        "Huangzhuyang"
    ],
    "name:zho_x_preferred":[
        "\u9ec3\u7af9\u6d0b"
    ],
    "wof:name":"Wong Chuk Yeung",
    "wof:placetype":"locality"
},
  "geometry": {"coordinates":[114.26618999999999,22.40703],"type":"Point"}
}