{
  "type": "Feature",
  "properties": {
    "gn:admin1_code":"NSK",
    "gn:asciiname":"Mok Tse Che",
    "gn:country_code":"HK",
    "gn:dem":70,
    "gn:feature_class":"P",
    "gn:feature_code":"PPL",
    "gn:name":"Mok Tse Che",
    "gn:population":0,
    "gn:timezone":"Asia/Hong_Kong",
    "iso:country":"HK",
    "name:und_x_variant":[
        "Mozheshe"
    ],
    "name:zho_x_preferred":[
        "\u83ab\u906e\u8f0b"
    ],
    "wof:name":"Mok Tse Che",
    "wof:placetype":"locality"
},
  "geometry": {"coordinates":[114.25185,22.34834],"type":"Point"}
}