{
  "type": "Feature",
  "properties": {
    "gn:admin1_code":"00",
    "gn:asciiname":"Mo Tat Wan",
    "gn:country_code":"HK",
    "gn:dem":18,
    "gn:feature_class":"P",
    "gn:feature_code":"PPL",
    "gn:name":"Mo Tat Wan",
    "gn:population":0,
    "gn:timezone":"Asia/Hong_Kong",
    "iso:country":"HK",
    "name:und_x_variant":[
        "Mau Tat Wan",
        "Mo Tat Wan",
        "Moda Wan"
    ],
    "name:zho_x_preferred":[
        "\u6a21\u9054\u7063"
    ],
    "name:zho_x_variant":[
        "\u6a21\u8fbe\u6e7e"
    ],
    "wof:name":"Mo Tat Wan",
    "wof:placetype":"locality"
},
  "geometry": {"coordinates":[114.14568,22.20756],"type":"Point"}
}