{
  "type": "Feature",
  "properties": {
    "gn:admin1_code":"NTP",
    "gn:asciiname":"Chung Mei Kok",
    "gn:country_code":"HK",
    "gn:dem":28,
    "gn:feature_class":"P",
    "gn:feature_code":"PPL",
    "gn:name":"Chung Mei Kok",
    "gn:population":0,
    "gn:timezone":"Asia/Hong_Kong",
    "iso:country":"HK",
    "name:und_x_variant":[
        "Chung Mei Kok Sheung Wai",
        "Chung Mei Kok",
        "Chongwei Jiao"
    ],
    "name:zho_x_preferred":[
        "\u6d8c\u5c3e\u89d2"
    ],
    "wof:name":"Chung Mei Kok",
    "wof:placetype":"locality"
},
  "geometry": {"coordinates":[114.35993999999999,22.47417],"type":"Point"}
}