{
  "type": "Feature",
  "properties": {
    "gn:admin1_code":"NSK",
    "gn:asciiname":"Tseung Kwan O",
    "gn:cc2":"HK",
    "gn:country_code":"HK",
    "gn:dem":19,
    "gn:feature_class":"P",
    "gn:feature_code":"PPL",
    "gn:name":"Tseung Kwan O",
    "gn:population":0,
    "gn:timezone":"Asia/Hong_Kong",
    "iso:country":"HK",
    "name:ceb_x_preferred":[
        "Junk Bay"
    ],
    "name:epo_x_preferred":[
        "Tseung Kvan"
    ],
    "name:fra_x_preferred":[
        "Tseung Kwan"
    ],
    "name:hak_x_preferred":[
        "Chi\u00f4ng-Ki\u00fbn-\u00c0u"
    ],
    "name:jpn_x_preferred":[
        "\u5c06\u8ecd\u6fb3"
    ],
    "name:srp_x_preferred":[
        "\u0426\u0435\u0443\u043d\u0433 \u041a\u0432\u0430\u043d"
    ],
    "name:swe_x_preferred":[
        "Junk Bay"
    ],
    "name:und_x_variant":[
        "Cheung Kwan O",
        "Cheung Kwan",
        "Chan ji",
        "Tseung Kwan O"
    ],
    "name:wuu_x_preferred":[
        "\u5c06\u519b\u6fb3"
    ],
    "name:zho_x_preferred":[
        "\u5c07\u8ecd\u6fb3"
    ],
    "wof:name":"Tseung Kwan O",
    "wof:placetype":"locality"
},
  "geometry": {"coordinates":[114.24992,22.32789],"type":"Point"}
}