{
  "type": "Feature",
  "properties": {
    "gn:admin1_code":"NYL",
    "gn:asciiname":"Shui Tsiu Lo Wai",
    "gn:country_code":"HK",
    "gn:dem":7,
    "gn:feature_class":"P",
    "gn:feature_code":"PPL",
    "gn:name":"Shui Tsiu Lo Wai",
    "gn:population":0,
    "gn:timezone":"Asia/Hong_Kong",
    "iso:country":"HK",
    "name:und_x_variant":[
        "Shuijiao Laowei"
    ],
    "name:zho_x_preferred":[
        "\u6c34\u8549\u8001\u570d"
    ],
    "name:zho_x_variant":[
        "\u6c34\u8549\u8001\u56f4"
    ],
    "wof:name":"Shui Tsiu Lo Wai",
    "wof:placetype":"locality"
},
  "geometry": {"coordinates":[114.03349,22.42648],"type":"Point"}
}