{
  "type": "Feature",
  "properties": {
    "iso:country":"HK",
    "name:und_x_variant":[
        "Tai Tan"
    ],
    "name:zho_x_preferred":[
        "\u5927\u7058"
    ],
    "name:zho_x_variant":[
        "\u5927\u6ee9"
    ],
    "qs:gn_country":"HK",
    "qs:gn_fcode":"PPL",
    "qs:gn_pop":0,
    "qs:name":"\u5927\u7058",
    "qs:name_adm0":"\u9999\u6e2f",
    "qs:name_adm1":"\u65b0\u754c",
    "qs:photos":507,
    "qs:photos_1k":103,
    "qs:photos_9k":2,
    "qs:photos_9r":5,
    "qs:photos_all":507,
    "qs:photos_sr":7,
    "qs:placetype":"Town",
    "qs:pop_sr":"0",
    "qs:woe_adm0":24865698,
    "wof:name":"\u5927\u7058",
    "wof:placetype":"locality"
},
  "geometry": {"coordinates":[114.33333,22.43333],"type":"Point"}
}