{
  "type": "Feature",
  "properties": {
    "gn:admin1_code":"NST",
    "gn:asciiname":"Wong Nai Tau",
    "gn:country_code":"HK",
    "gn:dem":45,
    "gn:feature_class":"P",
    "gn:feature_code":"PPL",
    "gn:name":"Wong Nai Tau",
    "gn:population":0,
    "gn:timezone":"Asia/Hong_Kong",
    "iso:country":"HK",
    "name:und_x_variant":[
        "Huangnitou"
    ],
    "name:zho_x_preferred":[
        "\u9ec3\u6ce5\u982d"
    ],
    "name:zho_x_variant":[
        "\u9ec4\u6ce5\u5934"
    ],
    "wof:name":"Wong Nai Tau",
    "wof:placetype":"locality"
},
  "geometry": {"coordinates":[114.21669,22.38214],"type":"Point"}
}