{
  "type": "Feature",
  "properties": {
    "gn:admin1_code":"00",
    "gn:asciiname":"Pak Lap",
    "gn:country_code":"HK",
    "gn:dem":19,
    "gn:feature_class":"P",
    "gn:feature_code":"PPL",
    "gn:name":"Pak Lap",
    "gn:population":0,
    "gn:timezone":"Asia/Hong_Kong",
    "iso:country":"HK",
    "wof:name":"Pak Lap",
    "wof:placetype":"locality"
},
  "geometry": {"coordinates":[114.34999999999999,22.35],"type":"Point"}
}