{
  "type": "Feature",
  "properties": {
    "gn:admin1_code":"NIS",
    "gn:asciiname":"Hang Mei",
    "gn:country_code":"HK",
    "gn:dem":48,
    "gn:feature_class":"P",
    "gn:feature_code":"PPL",
    "gn:name":"Hang Mei",
    "gn:population":0,
    "gn:timezone":"Asia/Hong_Kong",
    "iso:country":"HK",
    "name:und_x_variant":[
        "Kengwei"
    ],
    "name:zho_x_preferred":[
        "\u5751\u5c3e"
    ],
    "wof:name":"Hang Mei",
    "wof:placetype":"locality"
},
  "geometry": {"coordinates":[113.87050000000001,22.25289],"type":"Point"}
}