{
  "type": "Feature",
  "properties": {
    "iso:country":"HK",
    "name:und_x_variant":[
        "San Lung Wai"
    ],
    "name:zho_x_preferred":[
        "\u65b0\u9686\u570d"
    ],
    "name:zho_x_variant":[
        "\u65b0\u9686\u56f4"
    ],
    "qs:gn_country":"HK",
    "qs:gn_fcode":"PPL",
    "qs:gn_pop":0,
    "qs:name":"\u65b0\u9f8d\u570d",
    "qs:name_adm0":"\u9999\u6e2f",
    "qs:name_adm1":"\u65b0\u754c",
    "qs:photos":40,
    "qs:photos_1k":8,
    "qs:photos_9k":1,
    "qs:photos_9r":2,
    "qs:photos_all":40,
    "qs:photos_sr":2,
    "qs:placetype":"Town",
    "qs:pop_sr":"0",
    "qs:woe_adm0":24865698,
    "wof:name":"\u65b0\u9f8d\u570d",
    "wof:placetype":"locality"
},
  "geometry": {"coordinates":[114.09999999999999,22.45],"type":"Point"}
}