{
  "type": "Feature",
  "properties": {
    "gn:admin1_code":"NIS",
    "gn:asciiname":"Wang Long",
    "gn:country_code":"HK",
    "gn:dem":13,
    "gn:feature_class":"P",
    "gn:feature_code":"PPL",
    "gn:name":"Wang Long",
    "gn:population":0,
    "gn:timezone":"Asia/Hong_Kong",
    "iso:country":"HK",
    "name:ara_x_preferred":[
        "\u0648\u0627\u0646\u063a \u0644\u0648\u0646\u063a"
    ],
    "name:nor_x_preferred":[
        "Wang Long"
    ],
    "name:und_x_variant":[
        "Henglang"
    ],
    "name:zho_x_preferred":[
        "\u6a6b\u5871"
    ],
    "wof:name":"Wang Long",
    "wof:placetype":"locality"
},
  "geometry": {"coordinates":[114.1131,22.2231],"type":"Point"}
}