{
  "type": "Feature",
  "properties": {
    "gn:admin1_code":"NYL",
    "gn:asciiname":"Yuen Long San Hui",
    "gn:cc2":"HK",
    "gn:country_code":"HK",
    "gn:dem":8,
    "gn:feature_class":"P",
    "gn:feature_code":"PPL",
    "gn:name":"Yuen Long San Hui",
    "gn:population":0,
    "gn:timezone":"Asia/Hong_Kong",
    "iso:country":"HK",
    "name:und_x_variant":[
        "Y\u00fcan-lang-hsin-hs\u00fc",
        "Yuen Long Town",
        "Yuen Long",
        "Yuen Long Market",
        "Yuen Long San Hui",
        "Yuanlang Xinxu",
        "Yuanlang"
    ],
    "name:zho_x_preferred":[
        "\u5143\u6717\u65b0\u589f"
    ],
    "name:zho_x_variant":[
        "\u5143\u6717"
    ],
    "wof:name":"Yuen Long San Hui",
    "wof:placetype":"locality"
},
  "geometry": {"coordinates":[114.03333000000001,22.43333],"type":"Point"}
}