{
  "type": "Feature",
  "properties": {
    "gn:admin1_code":"NYL",
    "gn:asciiname":"Sheung Tsuen",
    "gn:country_code":"HK",
    "gn:dem":35,
    "gn:feature_class":"P",
    "gn:feature_code":"PPL",
    "gn:name":"Sheung Tsuen",
    "gn:population":0,
    "gn:timezone":"Asia/Hong_Kong",
    "iso:country":"HK",
    "name:und_x_variant":[
        "Shangcun"
    ],
    "name:zho_x_preferred":[
        "\u4e0a\u6751"
    ],
    "wof:name":"Sheung Tsuen",
    "wof:placetype":"locality"
},
  "geometry": {"coordinates":[114.09944,22.43301],"type":"Point"}
}