{
  "type": "Feature",
  "properties": {
    "iso:country":"HK",
    "name:eng_x_preferred":[
        "Ma Liu Shui"
    ],
    "name:heb_x_preferred":[
        "\u725b\u6c60\u7063"
    ],
    "name:nld_x_preferred":[
        "Ma Liu Shui"
    ],
    "name:unk_x_variant":[
        "Ma Liu Shui"
    ],
    "name:yue_x_preferred":[
        "\u99ac\u6599\u6c34"
    ],
    "name:zho_x_preferred":[
        "\u99ac\u6599\u6c34"
    ],
    "name:zho_x_variant":[
        "\u9a6c\u6599\u6c34"
    ],
    "qs:gn_country":"HK",
    "qs:gn_fcode":"PPL",
    "qs:gn_pop":0,
    "qs:name":"\u99ac\u6599\u6c34",
    "qs:name_adm0":"\u9999\u6e2f",
    "qs:name_adm1":"\u65b0\u754c",
    "qs:photos":916,
    "qs:photos_1k":186,
    "qs:photos_9k":4,
    "qs:photos_9r":6,
    "qs:photos_all":916,
    "qs:photos_sr":10,
    "qs:placetype":"Town",
    "qs:pop_sr":"0",
    "qs:woe_adm0":24865698,
    "wof:name":"\u99ac\u6599\u6c34",
    "wof:placetype":"locality"
},
  "geometry": {"coordinates":[114.21666999999999,22.41667],"type":"Point"}
}