{
  "type": "Feature",
  "properties": {
    "gn:admin1_code":"NNO",
    "gn:asciiname":"Lin Ma Hang",
    "gn:country_code":"HK",
    "gn:dem":64,
    "gn:feature_class":"P",
    "gn:feature_code":"PPL",
    "gn:name":"Lin Ma Hang",
    "gn:population":0,
    "gn:timezone":"Asia/Hong_Kong",
    "iso:country":"HK",
    "name:und_x_variant":[
        "Lianmakeng"
    ],
    "name:zho_x_preferred":[
        "\u84ee\u9ebb\u5751"
    ],
    "name:zho_x_variant":[
        "\u83b2\u9ebb\u5751"
    ],
    "wof:name":"Lin Ma Hang",
    "wof:placetype":"locality"
},
  "geometry": {"coordinates":[114.18387,22.54979],"type":"Point"}
}