{
  "type": "Feature",
  "properties": {
    "gn:admin1_code":"NTP",
    "gn:asciiname":"Tsiu Lam",
    "gn:country_code":"HK",
    "gn:dem":72,
    "gn:feature_class":"P",
    "gn:feature_code":"PPL",
    "gn:name":"Tsiu Lam",
    "gn:population":0,
    "gn:timezone":"Asia/Hong_Kong",
    "iso:country":"HK",
    "name:und_x_variant":[
        "A Shan Tsiu Lam",
        "A Shan Shan Tsiu Lam",
        "Tsiu Lam",
        "Jiaolin"
    ],
    "name:zho_x_preferred":[
        "\u8549\u6797"
    ],
    "wof:name":"Tsiu Lam",
    "wof:placetype":"locality"
},
  "geometry": {"coordinates":[114.19517,22.47112000000001],"type":"Point"}
}