{
  "type": "Feature",
  "properties": {
    "gn:admin1_code":"NTP",
    "gn:asciiname":"Ha Wun Yiu",
    "gn:country_code":"HK",
    "gn:dem":50,
    "gn:feature_class":"P",
    "gn:feature_code":"PPL",
    "gn:name":"Ha Wun Yiu",
    "gn:population":0,
    "gn:timezone":"Asia/Hong_Kong",
    "iso:country":"HK",
    "name:und_x_variant":[
        "Xiawanyao"
    ],
    "name:zho_x_preferred":[
        "\u4e0b\u7897\u7ab0"
    ],
    "name:zho_x_variant":[
        "\u4e0b\u7897\u7a91"
    ],
    "wof:name":"Ha Wun Yiu",
    "wof:placetype":"locality"
},
  "geometry": {"coordinates":[114.16667,22.43333],"type":"Point"}
}