{
  "type": "Feature",
  "properties": {
    "iso:country":"HK",
    "name:unk_x_variant":[
        "Pak Tam"
    ],
    "name:zho_x_preferred":[
        "\u5317\u6f6d"
    ],
    "name:zho_x_variant":[
        "\u5317\u8c2d"
    ],
    "qs:gn_country":"HK",
    "qs:gn_fcode":"PPL",
    "qs:gn_pop":0,
    "qs:name":"\u5317\u6f6d",
    "qs:name_adm0":"\u9999\u6e2f",
    "qs:name_adm1":"\u65b0\u754c",
    "qs:photos":189,
    "qs:photos_1k":38,
    "qs:photos_9k":1,
    "qs:photos_9r":4,
    "qs:photos_all":189,
    "qs:photos_sr":4,
    "qs:placetype":"Town",
    "qs:pop_sr":"0",
    "qs:woe_adm0":24865698,
    "wof:name":"\u5317\u6f6d",
    "wof:placetype":"locality"
},
  "geometry": {"coordinates":[114.31667,22.41667],"type":"Point"}
}