{
  "type": "Feature",
  "properties": {
    "iso:country":"HK",
    "name:dut_x_preferred":[
        "Fung Hang"
    ],
    "name:eng_x_preferred":[
        "Fung Hang"
    ],
    "name:unk_x_variant":[
        "Fung Hang"
    ],
    "name:zho_x_preferred":[
        "\u98a8\u5751"
    ],
    "name:zho_x_variant":[
        "\u98ce\u5751"
    ],
    "qs:gn_country":"HK",
    "qs:gn_fcode":"PPL",
    "qs:gn_pop":0,
    "qs:name":"\u9cf3\u676d",
    "qs:name_adm0":"\u9999\u6e2f",
    "qs:name_adm1":"\u65b0\u754c",
    "qs:photos":444,
    "qs:photos_1k":90,
    "qs:photos_9k":2,
    "qs:photos_9r":5,
    "qs:photos_all":444,
    "qs:photos_sr":6,
    "qs:placetype":"Town",
    "qs:pop_sr":"0",
    "qs:woe_adm0":24865698,
    "wof:name":"\u9cf3\u676d",
    "wof:placetype":"locality"
},
  "geometry": {"coordinates":[114.21666999999999,22.53333],"type":"Point"}
}