{
  "type": "Feature",
  "properties": {
    "gn:admin1_code":"NTP",
    "gn:asciiname":"Tai Om",
    "gn:country_code":"HK",
    "gn:dem":76,
    "gn:feature_class":"P",
    "gn:feature_code":"PPL",
    "gn:name":"Tai Om",
    "gn:population":0,
    "gn:timezone":"Asia/Hong_Kong",
    "iso:country":"HK",
    "name:und_x_variant":[
        "Da\u2019an"
    ],
    "name:zho_x_preferred":[
        "\u5927\u83f4"
    ],
    "wof:name":"Tai Om",
    "wof:placetype":"locality"
},
  "geometry": {"coordinates":[114.13446,22.44229],"type":"Point"}
}