{
  "type": "Feature",
  "properties": {
    "gn:admin1_code":"NYL",
    "gn:asciiname":"Wing Ning Tsuen",
    "gn:country_code":"HK",
    "gn:dem":20,
    "gn:feature_class":"P",
    "gn:feature_code":"PPL",
    "gn:name":"Wing Ning Tsuen",
    "gn:population":0,
    "gn:timezone":"Asia/Hong_Kong",
    "iso:country":"HK",
    "name:und_x_variant":[
        "Yongningcun"
    ],
    "name:zho_x_preferred":[
        "\u6c38\u5be7\u6751"
    ],
    "name:zho_x_variant":[
        "\u6c38\u5b81\u6751"
    ],
    "wof:name":"Wing Ning Tsuen",
    "wof:placetype":"locality"
},
  "geometry": {"coordinates":[114.01602,22.4507],"type":"Point"}
}