{
  "type": "Feature",
  "properties": {
    "iso:country":"HK",
    "name:eng_x_preferred":[
        "Ta Kwu Ling"
    ],
    "name:zho_hk_x_preferred":[
        "\u6253\u9f13\u5dba"
    ],
    "qs:gn_pop":0,
    "qs:name":"\u6253\u9f13\u5dba",
    "qs:name_adm0":"\u9999\u6e2f",
    "qs:name_adm1":"\u65b0\u754c",
    "qs:photos":37,
    "qs:photos_1k":7,
    "qs:photos_9k":1,
    "qs:photos_9r":2,
    "qs:photos_all":37,
    "qs:photos_sr":2,
    "qs:placetype":"Town",
    "qs:pop_sr":"0",
    "qs:woe_adm0":24865698,
    "wof:name":"Ta Kwu Ling",
    "wof:placetype":"locality"
},
  "geometry": {"coordinates":[114.248971,22.345034],"type":"Point"}
}