{
  "type": "Feature",
  "properties": {
    "gn:admin1_code":"NTP",
    "gn:asciiname":"O Tau",
    "gn:country_code":"HK",
    "gn:dem":40,
    "gn:feature_class":"P",
    "gn:feature_code":"PPL",
    "gn:name":"O Tau",
    "gn:population":0,
    "gn:timezone":"Asia/Hong_Kong",
    "iso:country":"HK",
    "name:und_x_variant":[
        "Aotou"
    ],
    "name:zho_x_preferred":[
        "\u6fb3\u982d"
    ],
    "name:zho_x_variant":[
        "\u6fb3\u5934"
    ],
    "wof:name":"O Tau",
    "wof:placetype":"locality"
},
  "geometry": {"coordinates":[114.28039,22.40075],"type":"Point"}
}