{
  "type": "Feature",
  "properties": {
    "iso:country":"HK",
    "name:eng_x_preferred":[
        "Ngau Shi Wu"
    ],
    "name:zho_hk_x_preferred":[
        "\u725b\u5c4e\u6e56"
    ],
    "qs:gn_pop":0,
    "qs:name":"\u725b\u5c4e\u6e56",
    "qs:name_adm0":"\u9999\u6e2f",
    "qs:name_adm1":"\u65b0\u754c",
    "qs:photos":480,
    "qs:photos_1k":97,
    "qs:photos_9k":2,
    "qs:photos_9r":5,
    "qs:photos_all":480,
    "qs:photos_sr":7,
    "qs:placetype":"Town",
    "qs:pop_sr":"0",
    "qs:woe_adm0":24865698,
    "wof:name":"Ngau Shi Wu",
    "wof:placetype":"locality"
},
  "geometry": {"coordinates":[114.243049,22.329752],"type":"Point"}
}