{
  "type": "Feature",
  "properties": {
    "gn:admin1_code":"NSK",
    "gn:asciiname":"Shek Pok Wai",
    "gn:country_code":"HK",
    "gn:dem":141,
    "gn:feature_class":"P",
    "gn:feature_code":"PPL",
    "gn:name":"Shek Pok Wai",
    "gn:population":0,
    "gn:timezone":"Asia/Hong_Kong",
    "iso:country":"HK",
    "wof:name":"Shek Pok Wai",
    "wof:placetype":"locality"
},
  "geometry": {"coordinates":[114.23333,22.35],"type":"Point"}
}