{
  "type": "Feature",
  "properties": {
    "gn:admin1_code":"NIS",
    "gn:asciiname":"Tai Pak",
    "gn:country_code":"HK",
    "gn:dem":56,
    "gn:feature_class":"P",
    "gn:feature_code":"PPL",
    "gn:name":"Tai Pak",
    "gn:population":0,
    "gn:timezone":"Asia/Hong_Kong",
    "iso:country":"HK",
    "name:und_x_variant":[
        "Dabai"
    ],
    "name:zho_x_preferred":[
        "\u5927\u767d"
    ],
    "wof:name":"Tai Pak",
    "wof:placetype":"locality"
},
  "geometry": {"coordinates":[114.01152999999999,22.29807000000001],"type":"Point"}
}