{
  "type": "Feature",
  "properties": {
    "gn:admin1_code":"NSK",
    "gn:asciiname":"She Tau",
    "gn:country_code":"HK",
    "gn:dem":46,
    "gn:feature_class":"P",
    "gn:feature_code":"PPL",
    "gn:name":"She Tau",
    "gn:population":0,
    "gn:timezone":"Asia/Hong_Kong",
    "iso:country":"HK",
    "name:und_x_variant":[
        "Shetou"
    ],
    "name:zho_x_preferred":[
        "\u86c7\u982d"
    ],
    "name:zho_x_variant":[
        "\u86c7\u5934"
    ],
    "wof:name":"She Tau",
    "wof:placetype":"locality"
},
  "geometry": {"coordinates":[114.30216,22.39811],"type":"Point"}
}