{
  "type": "Feature",
  "properties": {
    "gn:admin1_code":"NSK",
    "gn:asciiname":"Wang Che",
    "gn:country_code":"HK",
    "gn:dem":110,
    "gn:feature_class":"P",
    "gn:feature_code":"PPL",
    "gn:name":"Wang Che",
    "gn:population":0,
    "gn:timezone":"Asia/Hong_Kong",
    "iso:country":"HK",
    "name:und_x_variant":[
        "Hengshe"
    ],
    "name:zho_x_preferred":[
        "\u6a6b\u8f0b"
    ],
    "wof:name":"Wang Che",
    "wof:placetype":"locality"
},
  "geometry": {"coordinates":[114.24027,22.35954],"type":"Point"}
}