{
  "type": "Feature",
  "properties": {
    "gn:admin1_code":"NIS",
    "gn:asciiname":"Fong Yuen",
    "gn:country_code":"HK",
    "gn:dem":20,
    "gn:feature_class":"P",
    "gn:feature_code":"PPL",
    "gn:name":"Fong Yuen",
    "gn:population":0,
    "gn:timezone":"Asia/Hong_Kong",
    "iso:country":"HK",
    "name:und_x_variant":[
        "Fangyuan"
    ],
    "name:zho_x_preferred":[
        "\u82b3\u5712"
    ],
    "name:zho_x_variant":[
        "\u82b3\u56ed"
    ],
    "wof:name":"Fong Yuen",
    "wof:placetype":"locality"
},
  "geometry": {"coordinates":[113.93317,22.27039],"type":"Point"}
}