{
  "type": "Feature",
  "properties": {
    "iso:country":"HK",
    "name:unk_x_variant":[
        "Cheung Lek"
    ],
    "name:zho_x_preferred":[
        "\u9577\u701d"
    ],
    "name:zho_x_variant":[
        "\u957f\u6ca5"
    ],
    "qs:gn_country":"HK",
    "qs:gn_fcode":"PPL",
    "qs:gn_pop":0,
    "qs:name":"\u9577\u701d",
    "qs:name_adm0":"\u9999\u6e2f",
    "qs:name_adm1":"\u65b0\u754c",
    "qs:photos":251,
    "qs:photos_1k":51,
    "qs:photos_9k":1,
    "qs:photos_9r":4,
    "qs:photos_all":251,
    "qs:photos_sr":5,
    "qs:placetype":"Town",
    "qs:pop_sr":"0",
    "qs:woe_adm0":24865698,
    "wof:name":"\u9577\u701d",
    "wof:placetype":"locality"
},
  "geometry": {"coordinates":[114.09999999999999,22.48333],"type":"Point"}
}