{
  "type": "Feature",
  "properties": {
    "gn:admin1_code":"NYL",
    "gn:asciiname":"Shui Tin Tsuen",
    "gn:country_code":"HK",
    "gn:dem":5,
    "gn:feature_class":"P",
    "gn:feature_code":"PPL",
    "gn:name":"Shui Tin Tsuen",
    "gn:population":0,
    "gn:timezone":"Asia/Hong_Kong",
    "iso:country":"HK",
    "name:und_x_variant":[
        "Shuitiancun"
    ],
    "name:zho_x_preferred":[
        "\u6c34\u7530\u6751"
    ],
    "wof:name":"Shui Tin Tsuen",
    "wof:placetype":"locality"
},
  "geometry": {"coordinates":[114.02082,22.44866],"type":"Point"}
}