{
  "type": "Feature",
  "properties": {
    "iso:country":"HK",
    "name:und_x_variant":[
        "Ngau Hom"
    ],
    "name:zho_x_preferred":[
        "\u9c32\u78e1"
    ],
    "name:zho_x_variant":[
        "\u9ccc\u78e1"
    ],
    "qs:gn_country":"HK",
    "qs:gn_fcode":"PPL",
    "qs:gn_pop":0,
    "qs:name":"\u9c32\u78e1",
    "qs:name_adm0":"\u9999\u6e2f",
    "qs:name_adm1":"\u65b0\u754c",
    "qs:photos":54,
    "qs:photos_1k":11,
    "qs:photos_9k":1,
    "qs:photos_9r":2,
    "qs:photos_all":54,
    "qs:photos_sr":2,
    "qs:placetype":"Town",
    "qs:pop_sr":"0",
    "qs:woe_adm0":24865698,
    "wof:name":"\u9c32\u78e1",
    "wof:placetype":"locality"
},
  "geometry": {"coordinates":[113.98333,22.46667],"type":"Point"}
}