{
  "type": "Feature",
  "properties": {
    "gn:admin1_code":"NTP",
    "gn:asciiname":"Tai Hom",
    "gn:country_code":"HK",
    "gn:dem":297,
    "gn:feature_class":"P",
    "gn:feature_code":"PPL",
    "gn:name":"Tai Hom",
    "gn:population":0,
    "gn:timezone":"Asia/Hong_Kong",
    "iso:country":"HK",
    "name:und_x_variant":[
        "Dakan"
    ],
    "name:zho_x_preferred":[
        "\u5927\u78e1"
    ],
    "wof:name":"Tai Hom",
    "wof:placetype":"locality"
},
  "geometry": {"coordinates":[114.31057,22.43389],"type":"Point"}
}