{
  "type": "Feature",
  "properties": {
    "gn:admin1_code":"NSK",
    "gn:asciiname":"Tai No Sheung Yeung",
    "gn:country_code":"HK",
    "gn:dem":306,
    "gn:feature_class":"P",
    "gn:feature_code":"PPL",
    "gn:name":"Tai No Sheung Yeung",
    "gn:population":0,
    "gn:timezone":"Asia/Hong_Kong",
    "iso:country":"HK",
    "name:und_x_variant":[
        "Danaoshangyang"
    ],
    "name:zho_x_preferred":[
        "\u5927\u8166\u4e0a\u6d0b"
    ],
    "name:zho_x_variant":[
        "\u5927\u8111\u4e0a\u6d0b"
    ],
    "wof:name":"Tai No Sheung Yeung",
    "wof:placetype":"locality"
},
  "geometry": {"coordinates":[114.23341000000001,22.36752000000001],"type":"Point"}
}