{
  "type": "Feature",
  "properties": {
    "iso:country":"HK",
    "name:unk_x_variant":[
        "Tai Po Tau"
    ],
    "name:zho_x_preferred":[
        "\u5927\u57d4\u982d"
    ],
    "name:zho_x_variant":[
        "\u5927\u57d4\u5934"
    ],
    "qs:gn_country":"HK",
    "qs:gn_fcode":"PPL",
    "qs:gn_pop":0,
    "qs:name":"\u5927\u57d4\u982d",
    "qs:name_adm0":"\u9999\u6e2f",
    "qs:name_adm1":"\u65b0\u754c",
    "qs:photos":406,
    "qs:photos_1k":82,
    "qs:photos_9k":2,
    "qs:photos_9r":5,
    "qs:photos_all":406,
    "qs:photos_sr":6,
    "qs:placetype":"Town",
    "qs:pop_sr":"0",
    "qs:woe_adm0":24865698,
    "wof:name":"\u5927\u57d4\u982d",
    "wof:placetype":"locality"
},
  "geometry": {"coordinates":[114.15000000000001,22.45],"type":"Point"}
}