{
  "type": "Feature",
  "properties": {
    "iso:country":"HK",
    "name:und_x_variant":[
        "San Tin"
    ],
    "name:zho_x_preferred":[
        "\u65b0\u7530"
    ],
    "qs:gn_country":"HK",
    "qs:gn_fcode":"PPL",
    "qs:gn_pop":0,
    "qs:name":"\u65b0\u7530\u570d",
    "qs:name_adm0":"\u9999\u6e2f",
    "qs:name_adm1":"\u65b0\u754c",
    "qs:photos":117,
    "qs:photos_1k":24,
    "qs:photos_9k":1,
    "qs:photos_9r":3,
    "qs:photos_all":117,
    "qs:photos_sr":3,
    "qs:placetype":"Town",
    "qs:pop_sr":"0",
    "qs:woe_adm0":24865698,
    "wof:name":"\u65b0\u7530\u570d",
    "wof:placetype":"locality"
},
  "geometry": {"coordinates":[114.18333,22.36667],"type":"Point"}
}