{
  "type": "Feature",
  "properties": {
    "gn:admin1_code":"NNO",
    "gn:asciiname":"Kuk Po",
    "gn:country_code":"HK",
    "gn:dem":18,
    "gn:feature_class":"P",
    "gn:feature_code":"PPL",
    "gn:name":"Kuk Po",
    "gn:population":0,
    "gn:timezone":"Asia/Hong_Kong",
    "iso:country":"HK",
    "name:und_x_variant":[
        "Gupu"
    ],
    "name:zho_x_preferred":[
        "\u8c37\u57d4"
    ],
    "wof:name":"Kuk Po",
    "wof:placetype":"locality"
},
  "geometry": {"coordinates":[114.23716,22.52736],"type":"Point"}
}