{
  "type": "Feature",
  "properties": {
    "gn:admin1_code":"NIS",
    "gn:asciiname":"Tai Wan To",
    "gn:country_code":"HK",
    "gn:dem":1,
    "gn:feature_class":"P",
    "gn:feature_code":"PPL",
    "gn:name":"Tai Wan To",
    "gn:population":0,
    "gn:timezone":"Asia/Hong_Kong",
    "iso:country":"HK",
    "name:und_x_variant":[
        "Dawandu"
    ],
    "name:zho_x_preferred":[
        "\u5927\u7063\u809a"
    ],
    "name:zho_x_variant":[
        "\u5927\u6e7e\u809a"
    ],
    "wof:name":"Tai Wan To",
    "wof:placetype":"locality"
},
  "geometry": {"coordinates":[114.11704,22.22055],"type":"Point"}
}