{
  "type": "Feature",
  "properties": {
    "gn:admin1_code":"NNO",
    "gn:asciiname":"Hoi Pui Leng",
    "gn:country_code":"HK",
    "gn:dem":14,
    "gn:feature_class":"P",
    "gn:feature_code":"PPL",
    "gn:name":"Hoi Pui Leng",
    "gn:population":0,
    "gn:timezone":"Asia/Hong_Kong",
    "iso:country":"HK",
    "name:und_x_variant":[
        "Haibei Ling"
    ],
    "name:zho_x_preferred":[
        "\u6d77\u80cc\u5dba"
    ],
    "name:zho_x_variant":[
        "\u6d77\u80cc\u5cad"
    ],
    "wof:name":"Hoi Pui Leng",
    "wof:placetype":"locality"
},
  "geometry": {"coordinates":[114.20643,22.52857],"type":"Point"}
}