{
  "type": "Feature",
  "properties": {
    "gn:admin1_code":"NYL",
    "gn:asciiname":"Shek Wu Wai",
    "gn:country_code":"HK",
    "gn:dem":20,
    "gn:feature_class":"P",
    "gn:feature_code":"PPL",
    "gn:name":"Shek Wu Wai",
    "gn:population":0,
    "gn:timezone":"Asia/Hong_Kong",
    "iso:country":"HK",
    "name:und_x_variant":[
        "Shihu Wei"
    ],
    "name:zho_x_preferred":[
        "\u77f3\u6e56\u570d"
    ],
    "name:zho_x_variant":[
        "\u77f3\u6e56\u56f4"
    ],
    "wof:name":"Shek Wu Wai",
    "wof:placetype":"locality"
},
  "geometry": {"coordinates":[114.07117,22.49188],"type":"Point"}
}