{
  "type": "Feature",
  "properties": {
    "gn:admin1_code":"NTM",
    "gn:asciiname":"Sam Shing Hui",
    "gn:cc2":"HK",
    "gn:country_code":"HK",
    "gn:dem":55,
    "gn:feature_class":"P",
    "gn:feature_code":"PPL",
    "gn:name":"Sam Shing Hui",
    "gn:population":0,
    "gn:timezone":"Asia/Hong_Kong",
    "iso:country":"HK",
    "name:und_x_variant":[
        "Sam Shing Hiu",
        "Sam Shing Hui"
    ],
    "wof:name":"Sam Shing Hui",
    "wof:placetype":"locality"
},
  "geometry": {"coordinates":[113.98333,22.38333],"type":"Point"}
}