{
  "type": "Feature",
  "properties": {
    "iso:country":"HK",
    "name:ita_x_preferred":[
        "Y\u014dko Asagami"
    ],
    "name:jpn_x_preferred":[
        "\u4e00\u9f8d\u658e\u6625\u6c34"
    ],
    "name:rus_x_preferred":[
        "\u0410\u0441\u0430\u0433\u0430\u043c\u0438"
    ],
    "name:unk_x_variant":[
        "Sheung Yeung"
    ],
    "name:zho_x_preferred":[
        "\u4e0a\u6d0b"
    ],
    "qs:gn_country":"HK",
    "qs:gn_fcode":"PPL",
    "qs:gn_pop":0,
    "qs:name":"\u4e0a\u6d0b",
    "qs:name_adm0":"\u9999\u6e2f",
    "qs:name_adm1":"\u65b0\u754c",
    "qs:photos":90,
    "qs:photos_1k":18,
    "qs:photos_9k":1,
    "qs:photos_9r":3,
    "qs:photos_all":90,
    "qs:photos_sr":3,
    "qs:placetype":"Town",
    "qs:pop_sr":"0",
    "qs:woe_adm0":24865698,
    "wof:name":"\u4e0a\u6d0b",
    "wof:placetype":"locality"
},
  "geometry": {"coordinates":[114.28333000000001,22.31667],"type":"Point"}
}