{
  "type": "Feature",
  "properties": {
    "iso:country":"HK",
    "name:unk_x_variant":[
        "Hoi Ha"
    ],
    "name:zho_x_preferred":[
        "\u6d77\u4e0b"
    ],
    "qs:gn_country":"HK",
    "qs:gn_fcode":"PPL",
    "qs:gn_pop":0,
    "qs:name":"\u6d77\u4e0b",
    "qs:name_adm0":"\u9999\u6e2f",
    "qs:name_adm1":"\u65b0\u754c",
    "qs:photos":2114,
    "qs:photos_1k":428,
    "qs:photos_9k":9,
    "qs:photos_9r":9,
    "qs:photos_all":2114,
    "qs:photos_sr":16,
    "qs:placetype":"Town",
    "qs:pop_sr":"0",
    "qs:woe_adm0":24865698,
    "wof:name":"\u6d77\u4e0b",
    "wof:placetype":"locality"
},
  "geometry": {"coordinates":[114.33333,22.46667],"type":"Point"}
}