{
  "type": "Feature",
  "properties": {
    "gn:admin1_code":"NNO",
    "gn:asciiname":"Kat O Sheung Wai",
    "gn:country_code":"HK",
    "gn:dem":11,
    "gn:feature_class":"P",
    "gn:feature_code":"PPL",
    "gn:name":"Kat O Sheung Wai",
    "gn:population":0,
    "gn:timezone":"Asia/Hong_Kong",
    "iso:country":"HK",
    "name:und_x_variant":[
        "Kat O",
        "Kat O Sheung Wai",
        "Ji\u2019ao"
    ],
    "name:zho_x_preferred":[
        "\u5409\u6fb3"
    ],
    "wof:name":"Kat O Sheung Wai",
    "wof:placetype":"locality"
},
  "geometry": {"coordinates":[114.29216,22.54627],"type":"Point"}
}