{
  "type": "Feature",
  "properties": {
    "iso:country":"HK",
    "name:und_x_variant":[
        "Ha Shan Kai Wat"
    ],
    "name:zho_x_preferred":[
        "\u4e0b\u5c71\u9e21\u4e59"
    ],
    "name:zho_x_variant":[
        "\u4e0a\u5c71\u96de\u4e59"
    ],
    "qs:gn_country":"HK",
    "qs:gn_fcode":"PPL",
    "qs:gn_pop":0,
    "qs:name":"\u4e0b\u5c71\u96de\u4e59",
    "qs:name_adm0":"\u9999\u6e2f",
    "qs:name_adm1":"\u65b0\u754c",
    "qs:photos":86,
    "qs:photos_1k":17,
    "qs:photos_9k":1,
    "qs:photos_9r":3,
    "qs:photos_all":86,
    "qs:photos_sr":3,
    "qs:placetype":"Town",
    "qs:pop_sr":"0",
    "qs:woe_adm0":24865698,
    "wof:name":"\u4e0b\u5c71\u96de\u4e59",
    "wof:placetype":"locality"
},
  "geometry": {"coordinates":[114.15000000000001,22.51667],"type":"Point"}
}