{
  "type": "Feature",
  "properties": {
    "iso:country":"HK",
    "name:unk_x_variant":[
        "Mau Tso Ngam"
    ],
    "name:zho_x_preferred":[
        "\u8302\u8349\u5ca9"
    ],
    "qs:gn_country":"HK",
    "qs:gn_fcode":"PPL",
    "qs:gn_pop":0,
    "qs:name":"\u8302\u8349\u5ca9",
    "qs:name_adm0":"\u9999\u6e2f",
    "qs:name_adm1":"\u65b0\u754c",
    "qs:photos":509,
    "qs:photos_1k":103,
    "qs:photos_9k":2,
    "qs:photos_9r":5,
    "qs:photos_all":509,
    "qs:photos_sr":7,
    "qs:placetype":"Town",
    "qs:pop_sr":"0",
    "qs:woe_adm0":24865698,
    "wof:name":"\u8302\u8349\u5ca9",
    "wof:placetype":"locality"
},
  "geometry": {"coordinates":[114.21666999999999,22.36667],"type":"Point"}
}