{
  "type": "Feature",
  "properties": {
    "iso:country":"HK",
    "name:unk_x_variant":[
        "Wong Chuk Long"
    ],
    "name:zho_x_preferred":[
        "\u9ec3\u7af9\u5871"
    ],
    "qs:gn_country":"HK",
    "qs:gn_fcode":"PPL",
    "qs:gn_pop":0,
    "qs:name":"\u9ec3\u7af9\u6717",
    "qs:name_adm0":"\u9999\u6e2f",
    "qs:name_adm1":"\u65b0\u754c",
    "qs:photos":688,
    "qs:photos_1k":139,
    "qs:photos_9k":3,
    "qs:photos_9r":5,
    "qs:photos_all":688,
    "qs:photos_sr":8,
    "qs:placetype":"Town",
    "qs:pop_sr":"0",
    "qs:woe_adm0":24865698,
    "wof:name":"\u9ec3\u7af9\u6717",
    "wof:placetype":"locality"
},
  "geometry": {"coordinates":[114.31667,22.43333],"type":"Point"}
}