{
  "type": "Feature",
  "properties": {
    "iso:country":"HK",
    "name:unk_x_variant":[
        "Chung Uk"
    ],
    "name:zho_x_preferred":[
        "\u937e\u5c4b"
    ],
    "name:zho_x_variant":[
        "\u949f\u5c4b"
    ],
    "qs:gn_country":"HK",
    "qs:gn_fcode":"PPL",
    "qs:gn_pop":0,
    "qs:name":"\u937e\u5c4b",
    "qs:name_adm0":"\u9999\u6e2f",
    "qs:name_adm1":"\u96e2\u5cf6",
    "qs:photos":1000,
    "qs:photos_1k":203,
    "qs:photos_9k":4,
    "qs:photos_9r":6,
    "qs:photos_all":1000,
    "qs:photos_sr":10,
    "qs:placetype":"Town",
    "qs:pop_sr":"0",
    "qs:woe_adm0":24865698,
    "wof:name":"\u937e\u5c4b",
    "wof:placetype":"locality"
},
  "geometry": {"coordinates":[113.86667,22.25],"type":"Point"}
}