{
  "type": "Feature",
  "properties": {
    "gn:admin1_code":"NTP",
    "gn:asciiname":"Po Sam Pai",
    "gn:country_code":"HK",
    "gn:dem":9,
    "gn:feature_class":"P",
    "gn:feature_code":"PPL",
    "gn:name":"Po Sam Pai",
    "gn:population":0,
    "gn:timezone":"Asia/Hong_Kong",
    "iso:country":"HK",
    "name:und_x_variant":[
        "Buxin Pai"
    ],
    "name:zho_x_preferred":[
        "\u5e03\u5fc3\u6392"
    ],
    "wof:name":"Po Sam Pai",
    "wof:placetype":"locality"
},
  "geometry": {"coordinates":[114.21005,22.47096],"type":"Point"}
}