{
  "type": "Feature",
  "properties": {
    "gn:admin1_code":"NTP",
    "gn:asciiname":"Lai Chi Chong",
    "gn:country_code":"HK",
    "gn:dem":39,
    "gn:feature_class":"P",
    "gn:feature_code":"PPL",
    "gn:name":"Lai Chi Chong",
    "gn:population":0,
    "gn:timezone":"Asia/Hong_Kong",
    "iso:country":"HK",
    "name:und_x_variant":[
        "Lai Chee Chong",
        "Lai Chi Chong",
        "Lizhizhuang"
    ],
    "name:zho_x_preferred":[
        "\u8354\u679d\u838a"
    ],
    "wof:name":"Lai Chi Chong",
    "wof:placetype":"locality"
},
  "geometry": {"coordinates":[114.30107,22.45121],"type":"Point"}
}