{
  "type": "Feature",
  "properties": {
    "gn:admin1_code":"NNO",
    "gn:asciiname":"Sheung Wo Hang",
    "gn:country_code":"HK",
    "gn:dem":19,
    "gn:feature_class":"P",
    "gn:feature_code":"PPL",
    "gn:name":"Sheung Wo Hang",
    "gn:population":0,
    "gn:timezone":"Asia/Hong_Kong",
    "iso:country":"HK",
    "name:und_x_variant":[
        "Shanghekeng"
    ],
    "name:zho_x_preferred":[
        "\u4e0a\u79be\u5751"
    ],
    "wof:name":"Sheung Wo Hang",
    "wof:placetype":"locality"
},
  "geometry": {"coordinates":[114.19539,22.52353],"type":"Point"}
}