{
  "type": "Feature",
  "properties": {
    "iso:country":"HK",
    "name:eng_x_preferred":[
        "Happy Valley"
    ],
    "name:zho_hk_x_preferred":[
        "\u8dd1\u99ac\u5730"
    ],
    "qs:gn_pop":0,
    "qs:name":"\u8dd1\u99ac\u5730",
    "qs:name_adm0":"\u9999\u6e2f",
    "qs:name_adm1":"\u6e2f\u5cf6",
    "qs:photos":4996,
    "qs:photos_1k":1000,
    "qs:photos_9k":22,
    "qs:photos_9r":14,
    "qs:photos_all":4996,
    "qs:photos_sr":24,
    "qs:placetype":"Town",
    "qs:pop_sr":"0",
    "qs:woe_adm0":24865698,
    "wof:name":"Happy Valley",
    "wof:placetype":"locality"
},
  "geometry": {"coordinates":[114.18396,22.278218],"type":"Point"}
}