{
  "type": "Feature",
  "properties": {
    "gn:admin1_code":"NYL",
    "gn:asciiname":"Pak Hok Chau",
    "gn:country_code":"HK",
    "gn:dem":-4,
    "gn:feature_class":"P",
    "gn:feature_code":"PPL",
    "gn:name":"Pak Hok Chau",
    "gn:population":0,
    "gn:timezone":"Asia/Hong_Kong",
    "iso:country":"HK",
    "name:und_x_variant":[
        "Baihe Zhou"
    ],
    "name:zho_x_preferred":[
        "\u767d\u9db4\u6d32"
    ],
    "name:zho_x_variant":[
        "\u767d\u9e64\u6d32"
    ],
    "wof:name":"Pak Hok Chau",
    "wof:placetype":"locality"
},
  "geometry": {"coordinates":[114.04577,22.48858],"type":"Point"}
}