{
  "type": "Feature",
  "properties": {
    "gn:admin1_code":"NST",
    "gn:asciiname":"Sha Tin Tau",
    "gn:country_code":"HK",
    "gn:dem":8,
    "gn:feature_class":"P",
    "gn:feature_code":"PPL",
    "gn:name":"Sha Tin Tau",
    "gn:population":0,
    "gn:timezone":"Asia/Hong_Kong",
    "iso:country":"HK",
    "name:und_x_variant":[
        "Shatiantou"
    ],
    "name:zho_x_preferred":[
        "\u6c99\u7530\u982d"
    ],
    "name:zho_x_variant":[
        "\u6c99\u7530\u5934"
    ],
    "wof:name":"Sha Tin Tau",
    "wof:placetype":"locality"
},
  "geometry": {"coordinates":[114.18858,22.3735],"type":"Point"}
}