{
  "type": "Feature",
  "properties": {
    "gn:admin1_code":"NYL",
    "gn:asciiname":"Ha Pak Nai",
    "gn:country_code":"HK",
    "gn:dem":10,
    "gn:feature_class":"P",
    "gn:feature_code":"PPL",
    "gn:name":"Ha Pak Nai",
    "gn:population":0,
    "gn:timezone":"Asia/Hong_Kong",
    "iso:country":"HK",
    "name:und_x_variant":[
        "Xiabaini",
        "Ha Pak Nai"
    ],
    "name:zho_x_preferred":[
        "\u4e0b\u767d\u6ce5"
    ],
    "wof:name":"Ha Pak Nai",
    "wof:placetype":"locality"
},
  "geometry": {"coordinates":[113.94515,22.4279],"type":"Point"}
}