{
  "type": "Feature",
  "properties": {
    "gn:admin1_code":"NNO",
    "gn:asciiname":"Ng Uk Tsuen",
    "gn:country_code":"HK",
    "gn:dem":14,
    "gn:feature_class":"P",
    "gn:feature_code":"PPL",
    "gn:name":"Ng Uk Tsuen",
    "gn:population":0,
    "gn:timezone":"Asia/Hong_Kong",
    "iso:country":"HK",
    "name:und_x_variant":[
        "Wuwu Cun"
    ],
    "name:zho_x_preferred":[
        "\u5433\u5c4b\u6751"
    ],
    "name:zho_x_variant":[
        "\u5434\u5c4b\u6751"
    ],
    "wof:name":"Ng Uk Tsuen",
    "wof:placetype":"locality"
},
  "geometry": {"coordinates":[114.17039,22.51316],"type":"Point"}
}