{
  "type": "Feature",
  "properties": {
    "gn:admin1_code":"NTP",
    "gn:asciiname":"Che Ha",
    "gn:country_code":"HK",
    "gn:dem":13,
    "gn:feature_class":"P",
    "gn:feature_code":"PPL",
    "gn:name":"Che Ha",
    "gn:population":0,
    "gn:timezone":"Asia/Hong_Kong",
    "iso:country":"HK",
    "name:und_x_variant":[
        "Shexia"
    ],
    "name:zho_x_preferred":[
        "\u8f0b\u4e0b"
    ],
    "wof:name":"Che Ha",
    "wof:placetype":"locality"
},
  "geometry": {"coordinates":[114.26264,22.43021],"type":"Point"}
}