{
  "type": "Feature",
  "properties": {
    "gn:admin1_code":"NIS",
    "gn:asciiname":"Mui Wo Kau Tsuen",
    "gn:country_code":"HK",
    "gn:dem":39,
    "gn:feature_class":"P",
    "gn:feature_code":"PPL",
    "gn:name":"Mui Wo Kau Tsuen",
    "gn:population":0,
    "gn:timezone":"Asia/Hong_Kong",
    "iso:country":"HK",
    "name:und_x_variant":[
        "Pak Ngau Heung",
        "Mui Wo Kau Tsuen",
        "Meiwo Jiucun"
    ],
    "name:zho_x_preferred":[
        "\u6885\u7aa9\u820a\u6751"
    ],
    "name:zho_x_variant":[
        "\u6885\u7a9d\u65e7\u6751"
    ],
    "wof:name":"Mui Wo Kau Tsuen",
    "wof:placetype":"locality"
},
  "geometry": {"coordinates":[113.98609,22.26886],"type":"Point"}
}