{
  "type": "Feature",
  "properties": {
    "gn:admin1_code":"NST",
    "gn:asciiname":"Ha Keng Hau",
    "gn:country_code":"HK",
    "gn:dem":14,
    "gn:feature_class":"P",
    "gn:feature_code":"PPL",
    "gn:name":"Ha Keng Hau",
    "gn:population":0,
    "gn:timezone":"Asia/Hong_Kong",
    "iso:country":"HK",
    "name:und_x_variant":[
        "Keng Hau",
        "Ha Keng Hau",
        "Xiajingkou"
    ],
    "name:zho_x_preferred":[
        "\u4e0b\u5f91\u53e3"
    ],
    "name:zho_x_variant":[
        "\u4e0b\u5f84\u53e3"
    ],
    "wof:name":"Ha Keng Hau",
    "wof:placetype":"locality"
},
  "geometry": {"coordinates":[114.17615000000001,22.36494],"type":"Point"}
}