{
  "type": "Feature",
  "properties": {
    "gn:admin1_code":"NTP",
    "gn:asciiname":"Sha Lan",
    "gn:country_code":"HK",
    "gn:dem":71,
    "gn:feature_class":"P",
    "gn:feature_code":"PPL",
    "gn:name":"Sha Lan",
    "gn:population":0,
    "gn:timezone":"Asia/Hong_Kong",
    "iso:country":"HK",
    "name:und_x_variant":[
        "Shalan"
    ],
    "name:zho_x_preferred":[
        "\u6c99\u6b04"
    ],
    "name:zho_x_variant":[
        "\u6c99\u680f"
    ],
    "wof:name":"Sha Lan",
    "wof:placetype":"locality"
},
  "geometry": {"coordinates":[114.19669,22.46526],"type":"Point"}
}