{
  "type": "Feature",
  "properties": {
    "gn:admin1_code":"NSK",
    "gn:asciiname":"Sha Ha",
    "gn:country_code":"HK",
    "gn:dem":55,
    "gn:feature_class":"P",
    "gn:feature_code":"PPL",
    "gn:name":"Sha Ha",
    "gn:population":0,
    "gn:timezone":"Asia/Hong_Kong",
    "iso:country":"HK",
    "name:und_x_variant":[
        "Shanxia"
    ],
    "name:zho_x_preferred":[
        "\u5c71\u4e0b"
    ],
    "wof:name":"Sha Ha",
    "wof:placetype":"locality"
},
  "geometry": {"coordinates":[114.26577,22.38413],"type":"Point"}
}