{
  "type": "Feature",
  "properties": {
    "gn:admin1_code":"KWT",
    "gn:asciiname":"Muk Wu",
    "gn:country_code":"HK",
    "gn:dem":11,
    "gn:feature_class":"P",
    "gn:feature_code":"PPL",
    "gn:name":"Muk Wu",
    "gn:population":0,
    "gn:timezone":"Asia/Hong_Kong",
    "iso:country":"HK",
    "name:und_x_variant":[
        "Muhu"
    ],
    "name:zho_x_preferred":[
        "\u6728\u6e56"
    ],
    "wof:name":"Muk Wu",
    "wof:placetype":"locality"
},
  "geometry": {"coordinates":[114.13419,22.53956],"type":"Point"}
}