{
  "type": "Feature",
  "properties": {
    "gn:admin1_code":"NYL",
    "gn:asciiname":"A Kung Tin",
    "gn:country_code":"HK",
    "gn:dem":42,
    "gn:feature_class":"P",
    "gn:feature_code":"PPL",
    "gn:name":"A Kung Tin",
    "gn:population":0,
    "gn:timezone":"Asia/Hong_Kong",
    "iso:country":"HK",
    "name:und_x_variant":[
        "Yagongtian"
    ],
    "name:zho_x_preferred":[
        "\u4e9e\u516c\u7530"
    ],
    "wof:name":"A Kung Tin",
    "wof:placetype":"locality"
},
  "geometry": {"coordinates":[114.10118,22.45509],"type":"Point"}
}