{
  "type": "Feature",
  "properties": {
    "gn:admin1_code":"NTP",
    "gn:asciiname":"Pak Kiu",
    "gn:country_code":"HK",
    "gn:dem":31,
    "gn:feature_class":"P",
    "gn:feature_code":"PPL",
    "gn:name":"Pak Kiu",
    "gn:population":0,
    "gn:timezone":"Asia/Hong_Kong",
    "iso:country":"HK",
    "name:und_x_variant":[
        "Baiqiao"
    ],
    "name:zho_x_preferred":[
        "\u767d\u6a4b"
    ],
    "name:zho_x_variant":[
        "\u767d\u6865"
    ],
    "wof:name":"Pak Kiu",
    "wof:placetype":"locality"
},
  "geometry": {"coordinates":[114.17198999999999,22.45141],"type":"Point"}
}