{
  "type": "Feature",
  "properties": {
    "gn:admin1_code":"NST",
    "gn:asciiname":"Kwai Po Lau",
    "gn:country_code":"HK",
    "gn:dem":33,
    "gn:feature_class":"P",
    "gn:feature_code":"PPL",
    "gn:name":"Kwai Po Lau",
    "gn:population":0,
    "gn:timezone":"Asia/Hong_Kong",
    "iso:country":"HK",
    "wof:name":"Kwai Po Lau",
    "wof:placetype":"locality"
},
  "geometry": {"coordinates":[114.23542999999999,22.42495],"type":"Point"}
}