{
  "type": "Feature",
  "properties": {
    "iso:country":"HK",
    "name:und_x_variant":[
        "Fat Tong Mun"
    ],
    "name:zho_x_preferred":[
        "\u5730\u5802\u5480"
    ],
    "qs:gn_country":"HK",
    "qs:gn_fcode":"PPL",
    "qs:gn_pop":0,
    "qs:name":"\u5730\u5858\u5480",
    "qs:name_adm0":"\u9999\u6e2f",
    "qs:name_adm1":"\u65b0\u754c",
    "qs:photos":1027,
    "qs:photos_1k":208,
    "qs:photos_9k":5,
    "qs:photos_9r":7,
    "qs:photos_all":1027,
    "qs:photos_sr":11,
    "qs:placetype":"Town",
    "qs:pop_sr":"0",
    "qs:woe_adm0":24865698,
    "wof:name":"\u5730\u5858\u5480",
    "wof:placetype":"locality"
},
  "geometry": {"coordinates":[114.28333000000001,22.26667],"type":"Point"}
}