{
  "type": "Feature",
  "properties": {
    "gn:admin1_code":"NYL",
    "gn:asciiname":"Ng Tung Chai",
    "gn:country_code":"HK",
    "gn:dem":109,
    "gn:feature_class":"P",
    "gn:feature_code":"PPL",
    "gn:name":"Ng Tung Chai",
    "gn:population":0,
    "gn:timezone":"Asia/Hong_Kong",
    "iso:country":"HK",
    "name:und_x_variant":[
        "Wutongzhai"
    ],
    "name:zho_x_preferred":[
        "\u68a7\u6850\u5be8"
    ],
    "wof:name":"Ng Tung Chai",
    "wof:placetype":"locality"
},
  "geometry": {"coordinates":[114.12669,22.43732],"type":"Point"}
}