{
  "type": "Feature",
  "properties": {
    "iso:country":"HK",
    "name:eng_x_preferred":[
        "Pak Nai"
    ],
    "name:zho_hk_x_preferred":[
        "\u767d\u6ce5"
    ],
    "qs:gn_pop":0,
    "qs:name":"\u767d\u6ce5",
    "qs:name_adm0":"\u9999\u6e2f",
    "qs:name_adm1":"\u65b0\u754c",
    "qs:photos":1528,
    "qs:photos_1k":310,
    "qs:photos_9k":7,
    "qs:photos_9r":8,
    "qs:photos_all":1528,
    "qs:photos_sr":13,
    "qs:placetype":"Town",
    "qs:pop_sr":"0",
    "qs:woe_adm0":24865698,
    "wof:name":"Pak Nai",
    "wof:placetype":"locality"
},
  "geometry": {"coordinates":[113.9500115,22.440562],"type":"Point"}
}