{
  "type": "Feature",
  "properties": {
    "gn:admin1_code":"00",
    "gn:asciiname":"Victoria",
    "gn:country_code":"HK",
    "gn:dem":31,
    "gn:feature_class":"P",
    "gn:feature_code":"PPL",
    "gn:name":"Victoria",
    "gn:population":0,
    "gn:timezone":"Asia/Hong_Kong",
    "iso:country":"HK",
    "name:eng_x_preferred":[
        "Victoria"
    ],
    "wof:name":"Victoria",
    "wof:placetype":"locality"
},
  "geometry": {"coordinates":[114.14417,22.2875],"type":"Point"}
}