{
  "type": "Feature",
  "properties": {
    "gn:admin1_code":"NNO",
    "gn:asciiname":"Luk Keng Wong Uk",
    "gn:country_code":"HK",
    "gn:dem":3,
    "gn:feature_class":"P",
    "gn:feature_code":"PPL",
    "gn:name":"Luk Keng Wong Uk",
    "gn:population":0,
    "gn:timezone":"Asia/Hong_Kong",
    "iso:country":"HK",
    "name:und_x_variant":[
        "Lawkong",
        "Lu-ching",
        "Luk Keng",
        "Luk Keng Wong Uk",
        "Lujinghuang Wu"
    ],
    "name:zho_x_preferred":[
        "\u5ed8\u9838\u9ec3\u5c4b"
    ],
    "name:zho_x_variant":[
        "\u5ed8\u9888\u9ec4\u5c4b"
    ],
    "wof:name":"Luk Keng Wong Uk",
    "wof:placetype":"locality"
},
  "geometry": {"coordinates":[114.21569,22.52102],"type":"Point"}
}