{
  "type": "Feature",
  "properties": {
    "gn:admin1_code":"NST",
    "gn:asciiname":"Wong Chuk Shan",
    "gn:country_code":"HK",
    "gn:dem":300,
    "gn:feature_class":"P",
    "gn:feature_code":"PPL",
    "gn:name":"Wong Chuk Shan",
    "gn:population":0,
    "gn:timezone":"Asia/Hong_Kong",
    "iso:country":"HK",
    "name:und_x_variant":[
        "Huangzhushan"
    ],
    "name:zho_x_preferred":[
        "\u9ec3\u7af9\u5c71"
    ],
    "wof:name":"Wong Chuk Shan",
    "wof:placetype":"locality"
},
  "geometry": {"coordinates":[114.23911,22.37962000000001],"type":"Point"}
}