{
  "type": "Feature",
  "properties": {
    "gn:admin1_code":"NNO",
    "gn:asciiname":"San Tsuen",
    "gn:country_code":"HK",
    "gn:dem":20,
    "gn:feature_class":"P",
    "gn:feature_code":"PPL",
    "gn:name":"San Tsuen",
    "gn:population":0,
    "gn:timezone":"Asia/Hong_Kong",
    "iso:country":"HK",
    "name:hye_x_preferred":[
        "\u054d\u0561\u0576 \u0551\u0578\u0582\u0565\u0576"
    ],
    "name:und_x_variant":[
        "Xincun"
    ],
    "name:zho_x_preferred":[
        "\u65b0\u6751"
    ],
    "wof:name":"San Tsuen",
    "wof:placetype":"locality"
},
  "geometry": {"coordinates":[114.21498,22.54413],"type":"Point"}
}