{
  "type": "Feature",
  "properties": {
    "iso:country":"HK",
    "qs:gn_pop":0,
    "qs:name":"\u6e23\u7538\u5c71",
    "qs:name_adm0":"\u9999\u6e2f",
    "qs:name_adm1":"\u6e2f\u5cf6",
    "qs:photos":3565,
    "qs:photos_1k":722,
    "qs:photos_9k":16,
    "qs:photos_9r":12,
    "qs:photos_all":3565,
    "qs:photos_sr":21,
    "qs:placetype":"Town",
    "qs:pop_sr":"0",
    "qs:woe_adm0":24865698,
    "wof:name":"\u6e23\u7538\u5c71",
    "wof:placetype":"locality"
},
  "geometry": {"coordinates":[114.19532700000001,22.269171],"type":"Point"}
}