{
  "type": "Feature",
  "properties": {
    "gn:admin1_code":"NYL",
    "gn:asciiname":"Nam Pin Wai",
    "gn:country_code":"HK",
    "gn:dem":4,
    "gn:feature_class":"P",
    "gn:feature_code":"PPL",
    "gn:name":"Nam Pin Wai",
    "gn:population":0,
    "gn:timezone":"Asia/Hong_Kong",
    "iso:country":"HK",
    "name:und_x_variant":[
        "Nanbianwei"
    ],
    "name:zho_x_preferred":[
        "\u5357\u908a\u570d"
    ],
    "name:zho_x_variant":[
        "\u5357\u8fb9\u56f4"
    ],
    "wof:name":"Nam Pin Wai",
    "wof:placetype":"locality"
},
  "geometry": {"coordinates":[114.03333000000001,22.45],"type":"Point"}
}