{
  "type": "Feature",
  "properties": {
    "iso:country":"HK",
    "name:eng_x_preferred":[
        "Cheung Lung Tin"
    ],
    "name:zho_hk_x_preferred":[
        "\u9577\u9f8d\u7530"
    ],
    "qs:gn_pop":0,
    "qs:name":"\u9577\u9f8d\u7530",
    "qs:name_adm0":"\u9999\u6e2f",
    "qs:name_adm1":"\u4e5d\u9f8d",
    "qs:photos":1041,
    "qs:photos_1k":211,
    "qs:photos_9k":5,
    "qs:photos_9r":7,
    "qs:photos_all":1041,
    "qs:photos_sr":11,
    "qs:placetype":"Town",
    "qs:pop_sr":"0",
    "qs:woe_adm0":24865698,
    "wof:name":"Cheung Lung Tin",
    "wof:placetype":"locality"
},
  "geometry": {"coordinates":[114.24354700000001,22.297176],"type":"Point"}
}