{
  "type": "Feature",
  "properties": {
    "gn:admin1_code":"NSK",
    "gn:asciiname":"San Uk",
    "gn:country_code":"HK",
    "gn:dem":54,
    "gn:feature_class":"P",
    "gn:feature_code":"PPL",
    "gn:name":"San Uk",
    "gn:population":0,
    "gn:timezone":"Asia/Hong_Kong",
    "iso:country":"HK",
    "name:und_x_variant":[
        "Xinwu"
    ],
    "name:zho_x_preferred":[
        "\u65b0\u5c4b"
    ],
    "wof:name":"San Uk",
    "wof:placetype":"locality"
},
  "geometry": {"coordinates":[114.26443999999999,22.38963],"type":"Point"}
}