{
  "type": "Feature",
  "properties": {
    "gn:admin1_code":"NNO",
    "gn:asciiname":"Yim Tso Ha",
    "gn:country_code":"HK",
    "gn:dem":0,
    "gn:feature_class":"P",
    "gn:feature_code":"PPL",
    "gn:name":"Yim Tso Ha",
    "gn:population":0,
    "gn:timezone":"Asia/Hong_Kong",
    "iso:country":"HK",
    "name:und_x_variant":[
        "Guzaoxia"
    ],
    "name:zho_x_preferred":[
        "\u76ec\u7076\u4e0b"
    ],
    "wof:name":"Yim Tso Ha",
    "wof:placetype":"locality"
},
  "geometry": {"coordinates":[114.2062,22.53156],"type":"Point"}
}