{
  "type": "Feature",
  "properties": {
    "iso:country":"HK",
    "qs:gn_pop":0,
    "qs:name":"\u5357\u751f\u570d",
    "qs:name_adm0":"\u9999\u6e2f",
    "qs:name_adm1":"\u65b0\u754c",
    "qs:photos":2014,
    "qs:photos_1k":408,
    "qs:photos_9k":9,
    "qs:photos_9r":9,
    "qs:photos_all":2014,
    "qs:photos_sr":15,
    "qs:placetype":"Town",
    "qs:pop_sr":"0",
    "qs:woe_adm0":24865698,
    "wof:name":"\u5357\u751f\u570d",
    "wof:placetype":"locality"
},
  "geometry": {"coordinates":[114.034843,22.458212],"type":"Point"}
}