{
  "type": "Feature",
  "properties": {
    "gn:admin1_code":"NSK",
    "gn:asciiname":"Leung Fai Tin",
    "gn:country_code":"HK",
    "gn:dem":97,
    "gn:feature_class":"P",
    "gn:feature_code":"PPL",
    "gn:name":"Leung Fai Tin",
    "gn:population":0,
    "gn:timezone":"Asia/Hong_Kong",
    "iso:country":"HK",
    "name:und_x_variant":[
        "Liangkuaitian"
    ],
    "name:zho_x_preferred":[
        "\u5169\u584a\u7530"
    ],
    "name:zho_x_variant":[
        "\u4e24\u5757\u7530"
    ],
    "wof:name":"Leung Fai Tin",
    "wof:placetype":"locality"
},
  "geometry": {"coordinates":[114.28798999999999,22.30161],"type":"Point"}
}