{
  "type": "Feature",
  "properties": {
    "gn:admin1_code":"NYL",
    "gn:asciiname":"Ng Ka Tsuen",
    "gn:country_code":"HK",
    "gn:dem":4,
    "gn:feature_class":"P",
    "gn:feature_code":"PPL",
    "gn:name":"Ng Ka Tsuen",
    "gn:population":0,
    "gn:timezone":"Asia/Hong_Kong",
    "iso:country":"HK",
    "name:und_x_variant":[
        "Wujiacun"
    ],
    "name:zho_x_preferred":[
        "\u5433\u5bb6\u6751"
    ],
    "name:zho_x_variant":[
        "\u5434\u5bb6\u6751"
    ],
    "wof:name":"Ng Ka Tsuen",
    "wof:placetype":"locality"
},
  "geometry": {"coordinates":[114.07076000000001,22.43727],"type":"Point"}
}