{
  "type": "Feature",
  "properties": {
    "iso:country":"HK",
    "name:eng_x_preferred":[
        "Ngong Ping"
    ],
    "name:fas_x_preferred":[
        "\u0627\u0646\u06af\u0646\u06af \u067e\u06cc\u0646\u06af"
    ],
    "name:heb_x_preferred":[
        "\u05e0\u05d2\u05d5\u05e0\u05d2 \u05e4\u05d9\u05e0\u05d2"
    ],
    "name:jpn_x_preferred":[
        "\u6602\u576a"
    ],
    "name:nld_x_preferred":[
        "Ngong Ping"
    ],
    "name:pol_x_preferred":[
        "Ngong Ping"
    ],
    "name:wuu_x_preferred":[
        "\u6602\u576a"
    ],
    "name:yue_x_preferred":[
        "\u6602\u576a"
    ],
    "name:zho_x_preferred":[
        "\u6602\u5e73"
    ],
    "name:zho_x_variant":[
        "\u6602\u576a"
    ],
    "qs:gn_country":"HK",
    "qs:gn_fcode":"PPL",
    "qs:gn_pop":0,
    "qs:name":"\u6602\u576a",
    "qs:name_adm0":"\u9999\u6e2f",
    "qs:name_adm1":"\u65b0\u754c",
    "qs:photos":88,
    "qs:photos_1k":18,
    "qs:photos_9k":1,
    "qs:photos_9r":3,
    "qs:photos_all":88,
    "qs:photos_sr":3,
    "qs:placetype":"Town",
    "qs:pop_sr":"0",
    "qs:woe_adm0":24865698,
    "wof:name":"\u6602\u576a",
    "wof:placetype":"locality"
},
  "geometry": {"coordinates":[114.25,22.38333],"type":"Point"}
}