{
  "type": "Feature",
  "properties": {
    "gn:admin1_code":"NIS",
    "gn:asciiname":"Peng Chau",
    "gn:cc2":"HK",
    "gn:country_code":"HK",
    "gn:dem":-9999,
    "gn:feature_class":"P",
    "gn:feature_code":"PPL",
    "gn:name":"Peng Chau",
    "gn:population":0,
    "gn:timezone":"Asia/Hong_Kong",
    "iso:country":"HK",
    "name:ceb_x_preferred":[
        "Peng Chau"
    ],
    "name:eus_x_preferred":[
        "Peng Chau"
    ],
    "name:ita_x_preferred":[
        "Peng Chau"
    ],
    "name:nld_x_preferred":[
        "Peng Chau"
    ],
    "name:nor_x_preferred":[
        "Peng Chau"
    ],
    "name:pol_x_preferred":[
        "Peng Chau"
    ],
    "name:spa_x_preferred":[
        "Peng Chau"
    ],
    "name:und_x_variant":[
        "Peang",
        "Ping Chau"
    ],
    "name:vie_x_preferred":[
        "B\u00ecnh Ch\u00e2u"
    ],
    "wof:name":"Peng Chau",
    "wof:placetype":"locality"
},
  "geometry": {"coordinates":[114.03333000000001,22.28333],"type":"Point"}
}