{
  "type": "Feature",
  "properties": {
    "gn:admin1_code":"NYL",
    "gn:asciiname":"Sha Kong Wai",
    "gn:country_code":"HK",
    "gn:dem":4,
    "gn:feature_class":"P",
    "gn:feature_code":"PPL",
    "gn:name":"Sha Kong Wai",
    "gn:population":0,
    "gn:timezone":"Asia/Hong_Kong",
    "iso:country":"HK",
    "name:und_x_variant":[
        "Shajiang Wei"
    ],
    "name:zho_x_preferred":[
        "\u6c99\u6c5f\u56f4"
    ],
    "name:zho_x_variant":[
        "\u6c99\u6c5f\u570d"
    ],
    "wof:name":"Sha Kong Wai",
    "wof:placetype":"locality"
},
  "geometry": {"coordinates":[113.99102000000001,22.46224],"type":"Point"}
}