{
  "type": "Feature",
  "properties": {
    "gn:admin1_code":"NNO",
    "gn:asciiname":"Fanling",
    "gn:cc2":"HK",
    "gn:country_code":"HK",
    "gn:dem":17,
    "gn:feature_class":"P",
    "gn:feature_code":"PPL",
    "gn:name":"Fanling",
    "gn:population":0,
    "gn:timezone":"Asia/Hong_Kong",
    "iso:country":"HK",
    "name:nld_x_preferred":[
        "Fanling"
    ],
    "name:und_x_variant":[
        "Fen-ling",
        "Fan Leng"
    ],
    "wof:name":"Fanling",
    "wof:placetype":"locality"
},
  "geometry": {"coordinates":[114.13949,22.49487],"type":"Point"}
}