{
  "type": "Feature",
  "properties": {
    "iso:country":"HK",
    "name:und_x_variant":[
        "Heung Yuen Wai"
    ],
    "name:zho_x_preferred":[
        "\u9999\u5712\u570d"
    ],
    "name:zho_x_variant":[
        "\u9999\u56ed\u56f4"
    ],
    "qs:gn_country":"HK",
    "qs:gn_fcode":"PPL",
    "qs:gn_pop":0,
    "qs:name":"\u9999\u5712\u570d",
    "qs:name_adm0":"\u9999\u6e2f",
    "qs:name_adm1":"\u65b0\u754c",
    "qs:photos":831,
    "qs:photos_1k":168,
    "qs:photos_9k":4,
    "qs:photos_9r":6,
    "qs:photos_all":831,
    "qs:photos_sr":9,
    "qs:placetype":"Town",
    "qs:pop_sr":"0",
    "qs:woe_adm0":24865698,
    "wof:name":"\u9999\u5712\u570d",
    "wof:placetype":"locality"
},
  "geometry": {"coordinates":[114.16667,22.55],"type":"Point"}
}