{
  "type": "Feature",
  "properties": {
    "gn:admin1_code":"00",
    "gn:asciiname":"Ma Tso Lung",
    "gn:country_code":"HK",
    "gn:dem":8,
    "gn:feature_class":"P",
    "gn:feature_code":"PPL",
    "gn:name":"Ma Tso Lung",
    "gn:population":0,
    "gn:timezone":"Asia/Hong_Kong",
    "iso:country":"HK",
    "name:und_x_variant":[
        "Macaotang"
    ],
    "name:zho_x_preferred":[
        "\u99ac\u8349\u5858"
    ],
    "name:zho_x_variant":[
        "\u9a6c\u8349\u5858"
    ],
    "wof:name":"Ma Tso Lung",
    "wof:placetype":"locality"
},
  "geometry": {"coordinates":[114.08333,22.53333],"type":"Point"}
}