{
  "type": "Feature",
  "properties": {
    "gn:admin1_code":"NYL",
    "gn:asciiname":"Tai Wai",
    "gn:country_code":"HK",
    "gn:dem":13,
    "gn:feature_class":"P",
    "gn:feature_code":"PPL",
    "gn:name":"Tai Wai",
    "gn:population":0,
    "gn:timezone":"Asia/Hong_Kong",
    "iso:country":"HK",
    "name:und_x_variant":[
        "Dawei"
    ],
    "name:zho_x_preferred":[
        "\u5927\u570d"
    ],
    "name:zho_x_variant":[
        "\u5927\u56f4"
    ],
    "wof:name":"Tai Wai",
    "wof:placetype":"locality"
},
  "geometry": {"coordinates":[114.03904,22.44668],"type":"Point"}
}