{
  "type": "Feature",
  "properties": {
    "iso:country":"HK",
    "name:unk_x_variant":[
        "Kau San Tei"
    ],
    "name:zho_x_preferred":[
        "\u72d7\u4f38\u5730"
    ],
    "qs:gn_country":"HK",
    "qs:gn_fcode":"PPL",
    "qs:gn_pop":0,
    "qs:name":"\u6ed8\u65b0\u5730",
    "qs:name_adm0":"\u9999\u6e2f",
    "qs:name_adm1":"\u96e2\u5cf6",
    "qs:photos":830,
    "qs:photos_1k":168,
    "qs:photos_9k":4,
    "qs:photos_9r":6,
    "qs:photos_all":830,
    "qs:photos_sr":9,
    "qs:placetype":"Town",
    "qs:pop_sr":"0",
    "qs:woe_adm0":24865698,
    "wof:name":"\u6ed8\u65b0\u5730",
    "wof:placetype":"locality"
},
  "geometry": {"coordinates":[113.86042,22.25995],"type":"Point"}
}