{
  "type": "Feature",
  "properties": {
    "iso:country":"HK",
    "name:eng_x_preferred":[
        "Mong Kok"
    ],
    "name:zho_hk_x_preferred":[
        "\u65fa\u89d2"
    ],
    "qs:gn_pop":0,
    "qs:name":"\u65fa\u89d2",
    "qs:name_adm0":"\u9999\u6e2f",
    "qs:name_adm1":"\u4e5d\u9f8d",
    "qs:photos":5000,
    "qs:photos_1k":1000,
    "qs:photos_9k":22,
    "qs:photos_9r":14,
    "qs:photos_all":5000,
    "qs:photos_sr":24,
    "qs:placetype":"Town",
    "qs:pop_sr":"0",
    "qs:woe_adm0":24865698,
    "wof:name":"Mong Kok",
    "wof:placetype":"locality"
},
  "geometry": {"coordinates":[114.16947399999999,22.32072],"type":"Point"}
}