{
  "type": "Feature",
  "properties": {
    "gn:admin1_code":"NYL",
    "gn:asciiname":"Kong Tau Tsuen",
    "gn:country_code":"HK",
    "gn:dem":8,
    "gn:feature_class":"P",
    "gn:feature_code":"PPL",
    "gn:name":"Kong Tau Tsuen",
    "gn:population":0,
    "gn:timezone":"Asia/Hong_Kong",
    "iso:country":"HK",
    "name:und_x_variant":[
        "Gangtoucun"
    ],
    "name:zho_x_preferred":[
        "\u6e2f\u982d\u6751"
    ],
    "name:zho_x_variant":[
        "\u6e2f\u5934\u6751"
    ],
    "wof:name":"Kong Tau Tsuen",
    "wof:placetype":"locality"
},
  "geometry": {"coordinates":[114.03845,22.43186],"type":"Point"}
}