{
  "type": "Feature",
  "properties": {
    "gn:admin1_code":"NIS",
    "gn:asciiname":"Ha Ling Pei",
    "gn:country_code":"HK",
    "gn:dem":13,
    "gn:feature_class":"P",
    "gn:feature_code":"PPL",
    "gn:name":"Ha Ling Pei",
    "gn:population":0,
    "gn:timezone":"Asia/Hong_Kong",
    "iso:country":"HK",
    "name:und_x_variant":[
        "Xialingpi"
    ],
    "name:zho_x_preferred":[
        "\u4e0b\u5dba\u76ae"
    ],
    "name:zho_x_variant":[
        "\u4e0b\u5cad\u76ae"
    ],
    "wof:name":"Ha Ling Pei",
    "wof:placetype":"locality"
},
  "geometry": {"coordinates":[113.93496,22.27789],"type":"Point"}
}