{
  "type": "Feature",
  "properties": {
    "gn:admin1_code":"NSK",
    "gn:asciiname":"Nam She",
    "gn:country_code":"HK",
    "gn:dem":13,
    "gn:feature_class":"P",
    "gn:feature_code":"PPL",
    "gn:name":"Nam She",
    "gn:population":0,
    "gn:timezone":"Asia/Hong_Kong",
    "iso:country":"HK",
    "name:und_x_variant":[
        "Ranshe"
    ],
    "name:zho_x_preferred":[
        "\u86ba\u86c7"
    ],
    "wof:name":"Nam She",
    "wof:placetype":"locality"
},
  "geometry": {"coordinates":[114.37123,22.43609],"type":"Point"}
}