{
  "type": "Feature",
  "properties": {
    "gn:admin1_code":"NYL",
    "gn:asciiname":"Tsz Tin Tsuen",
    "gn:country_code":"HK",
    "gn:dem":9,
    "gn:feature_class":"P",
    "gn:feature_code":"PPL",
    "gn:name":"Tsz Tin Tsuen",
    "gn:population":0,
    "gn:timezone":"Asia/Hong_Kong",
    "iso:country":"HK",
    "name:und_x_variant":[
        "Zitiancun"
    ],
    "name:zho_x_preferred":[
        "\u7d2b\u7530\u6751"
    ],
    "wof:name":"Tsz Tin Tsuen",
    "wof:placetype":"locality"
},
  "geometry": {"coordinates":[113.97631,22.41643],"type":"Point"}
}