{
  "type": "Feature",
  "properties": {
    "gn:admin1_code":"NSK",
    "gn:asciiname":"Chuk Yuen",
    "gn:country_code":"HK",
    "gn:dem":62,
    "gn:feature_class":"P",
    "gn:feature_code":"PPL",
    "gn:name":"Chuk Yuen",
    "gn:population":0,
    "gn:timezone":"Asia/Hong_Kong",
    "iso:country":"HK",
    "name:und_x_variant":[
        "Zhuyuan"
    ],
    "name:zho_x_preferred":[
        "\u7af9\u5712"
    ],
    "name:zho_x_variant":[
        "\u7af9\u56ed"
    ],
    "wof:name":"Chuk Yuen",
    "wof:placetype":"locality"
},
  "geometry": {"coordinates":[114.23671000000002,22.35458],"type":"Point"}
}