{
  "type": "Feature",
  "properties": {
    "gn:admin1_code":"NST",
    "gn:asciiname":"Heung Fan Liu",
    "gn:country_code":"HK",
    "gn:dem":44,
    "gn:feature_class":"P",
    "gn:feature_code":"PPL",
    "gn:name":"Heung Fan Liu",
    "gn:population":0,
    "gn:timezone":"Asia/Hong_Kong",
    "iso:country":"HK",
    "name:und_x_variant":[
        "Xiangfenliao"
    ],
    "name:zho_x_preferred":[
        "\u9999\u7c89\u5bee"
    ],
    "wof:name":"Heung Fan Liu",
    "wof:placetype":"locality"
},
  "geometry": {"coordinates":[114.16743999999998,22.37792],"type":"Point"}
}