{
  "type": "Feature",
  "properties": {
    "gn:admin1_code":"NIS",
    "gn:asciiname":"Tsin Yue Wan",
    "gn:country_code":"HK",
    "gn:dem":18,
    "gn:feature_class":"P",
    "gn:feature_code":"PPL",
    "gn:name":"Tsin Yue Wan",
    "gn:population":0,
    "gn:timezone":"Asia/Hong_Kong",
    "iso:country":"HK",
    "name:und_x_variant":[
        "Jianyu Wan"
    ],
    "name:zho_x_preferred":[
        "\u714e\u9b5a\u7063"
    ],
    "name:zho_x_variant":[
        "\u714e\u9c7c\u6e7e"
    ],
    "wof:name":"Tsin Yue Wan",
    "wof:placetype":"locality"
},
  "geometry": {"coordinates":[113.84399999999999,22.21188],"type":"Point"}
}