{
  "type": "Feature",
  "properties": {
    "gn:admin1_code":"00",
    "gn:asciiname":"Muk Wu Chuen Yiu",
    "gn:country_code":"HK",
    "gn:dem":13,
    "gn:feature_class":"P",
    "gn:feature_code":"PPL",
    "gn:name":"Muk Wu Chuen Yiu",
    "gn:population":0,
    "gn:timezone":"Asia/Hong_Kong",
    "iso:country":"HK",
    "wof:name":"Muk Wu Chuen Yiu",
    "wof:placetype":"locality"
},
  "geometry": {"coordinates":[114.13333,22.55],"type":"Point"}
}